[
{
  "fields": {
    "question": "Have you been to the symphony before?"
  },
  "model": "appcode.question",
  "pk": 1
},
{
  "fields": {
    "question": "How'd that go?"
  },
  "model": "appcode.question",
  "pk": 2
},
{
  "fields": {
    "question": "What are Saturdays for?"
  },
  "model": "appcode.question",
  "pk": 3
},
{
  "fields": {
    "question": "How old are they?"
  },
  "model": "appcode.question",
  "pk": 4
},
{
  "fields": {
    "question": "Which Beethoven are you most familiar with?"
  },
  "model": "appcode.question",
  "pk": 5
},
{
  "fields": {
    "question": "Which of these doesn't belong at the symphony?"
  },
  "model": "appcode.question",
  "pk": 6
},
{
  "fields": {
    "question": "If you had to pick a movie to watch tonight, what would it be?"
  },
  "model": "appcode.question",
  "pk": 7
},
{
  "fields": {
    "question": "Are you seeking light entertainment, or do you want to feel something?"
  },
  "model": "appcode.question",
  "pk": 8
},
{
  "fields": {
    "question": "What do you want to know more about?"
  },
  "model": "appcode.question",
  "pk": 10
},
{
  "fields": {
    "question": "Which show are you seeing?"
  },
  "model": "appcode.question",
  "pk": 11
},
{
  "fields": {
    "question": "Where are the best seats in the house?"
  },
  "model": "appcode.question",
  "pk": 12
},
{
  "fields": {
    "question": "What's your favourite musical insult?"
  },
  "model": "appcode.question",
  "pk": 13
},
{
  "fields": {
    "question": "Redirect"
  },
  "model": "appcode.question",
  "pk": 666
},
{
  "fields": {
    "answer": "Yeah!",
    "comment": "",
    "protip": "",
    "redirect_url_if_no_new_question": "",
    "old_question": 1,
    "new_question": 2
  },
  "model": "appcode.answer",
  "pk": 1
},
{
  "fields": {
    "answer": "Not even once",
    "comment": "But you'll try anything once, right?",
    "protip": "",
    "redirect_url_if_no_new_question": "",
    "old_question": 1,
    "new_question": 3
  },
  "model": "appcode.answer",
  "pk": 2
},
{
  "fields": {
    "answer": "Maybe when I was a kid",
    "comment": "Kinda like that one time you saw a Shakespeare play.",
    "protip": "",
    "redirect_url_if_no_new_question": "",
    "old_question": 1,
    "new_question": 3
  },
  "model": "appcode.answer",
  "pk": 3
},
{
  "fields": {
    "answer": "Don't know-I fell asleep.",
    "comment": "Yeah, I've been there.",
    "protip": "",
    "redirect_url_if_no_new_question": "",
    "old_question": 2,
    "new_question": 3
  },
  "model": "appcode.answer",
  "pk": 4
},
{
  "fields": {
    "answer": "Loved it!",
    "comment": "",
    "protip": "",
    "redirect_url_if_no_new_question": "",
    "old_question": 2,
    "new_question": 3
  },
  "model": "appcode.answer",
  "pk": 5
},
{
  "fields": {
    "answer": "It didn't exactly blow my mind. ",
    "comment": "Guess what? It's way less boring now!",
    "protip": "",
    "redirect_url_if_no_new_question": "",
    "old_question": 2,
    "new_question": 3
  },
  "model": "appcode.answer",
  "pk": 6
},
{
  "fields": {
    "answer": "Chilling with friends",
    "comment": "BBQs? Board games? Beers? Whatever it is, I'm in",
    "protip": "",
    "redirect_url_if_no_new_question": "",
    "old_question": 3,
    "new_question": 5
  },
  "model": "appcode.answer",
  "pk": 7
},
{
  "fields": {
    "answer": "Going out and partying hard",
    "comment": "Woooo!",
    "protip": "",
    "redirect_url_if_no_new_question": "",
    "old_question": 3,
    "new_question": 5
  },
  "model": "appcode.answer",
  "pk": 8
},
{
  "fields": {
    "answer": "Soaking up some culture ",
    "comment": "",
    "protip": "",
    "redirect_url_if_no_new_question": "",
    "old_question": 3,
    "new_question": 5
  },
  "model": "appcode.answer",
  "pk": 9
},
{
  "fields": {
    "answer": "Binge-watching Netflix",
    "comment": " They just added the next season of Brooklyn Nine-Nine. How can you not?",
    "protip": "",
    "redirect_url_if_no_new_question": "",
    "old_question": 3,
    "new_question": 5
  },
  "model": "appcode.answer",
  "pk": 10
},
{
  "fields": {
    "answer": "Time with the kids",
    "comment": "Aww, cute.",
    "protip": "",
    "redirect_url_if_no_new_question": "",
    "old_question": 3,
    "new_question": 4
  },
  "model": "appcode.answer",
  "pk": 11
},
{
  "fields": {
    "answer": "Tiny toddlers",
    "comment": "",
    "protip": "",
    "redirect_url_if_no_new_question": "",
    "old_question": 4,
    "new_question": 5
  },
  "model": "appcode.answer",
  "pk": 12
},
{
  "fields": {
    "answer": "Elementary school age",
    "comment": "",
    "protip": "",
    "redirect_url_if_no_new_question": "",
    "old_question": 4,
    "new_question": 5
  },
  "model": "appcode.answer",
  "pk": 13
},
{
  "fields": {
    "answer": "Teens",
    "comment": "",
    "protip": "",
    "redirect_url_if_no_new_question": "",
    "old_question": 4,
    "new_question": 5
  },
  "model": "appcode.answer",
  "pk": 14
},
{
  "fields": {
    "answer": "We're all grown-ups now",
    "comment": "",
    "protip": "",
    "redirect_url_if_no_new_question": "",
    "old_question": 4,
    "new_question": 5
  },
  "model": "appcode.answer",
  "pk": 15
},
{
  "fields": {
    "answer": "The brilliant, hot-tempered composer",
    "comment": "Protip: Come to the Prelude to learn more about how the same composer who threw soup at his waiter wrote music that threw the all the rules out the window. ",
    "protip": "",
    "redirect_url_if_no_new_question": "",
    "old_question": 5,
    "new_question": 6
  },
  "model": "appcode.answer",
  "pk": 16
},
{
  "fields": {
    "answer": "The lovable Saint Bernard who stars in a movie",
    "comment": "Protip: Come to the Prelude to learn more about how the same composer who threw soup at his waiter wrote music that threw the all the rules out the window. ",
    "protip": "",
    "redirect_url_if_no_new_question": "",
    "old_question": 5,
    "new_question": 6
  },
  "model": "appcode.answer",
  "pk": 17
},
{
  "fields": {
    "answer": "Beers in the theatre",
    "comment": "Did we fool you? You can do all these things at the symphony! Protip: Pre-order drinks for intermission so that they're ready the moment you are.",
    "protip": "",
    "redirect_url_if_no_new_question": "",
    "old_question": 6,
    "new_question": 7
  },
  "model": "appcode.answer",
  "pk": 18
},
{
  "fields": {
    "answer": "Jeans and T's",
    "comment": "Did we fool you? You can do all these things at the symphony! Protip: Pre-order drinks for intermission so that they're ready the moment you are.",
    "protip": "",
    "redirect_url_if_no_new_question": "",
    "old_question": 6,
    "new_question": 7
  },
  "model": "appcode.answer",
  "pk": 19
},
{
  "fields": {
    "answer": "Pop music and silent films",
    "comment": "Did we fool you? You can do all these things at the symphony! Protip: Pre-order drinks for intermission so that they're ready the moment you are.",
    "protip": "",
    "redirect_url_if_no_new_question": "",
    "old_question": 6,
    "new_question": 7
  },
  "model": "appcode.answer",
  "pk": 20
},
{
  "fields": {
    "answer": "Ice cream bars",
    "comment": "Did we fool you? You can do all these things at the symphony! Protip: Pre-order drinks for intermission so that they're ready the moment you are.",
    "protip": "",
    "redirect_url_if_no_new_question": "",
    "old_question": 6,
    "new_question": 7
  },
  "model": "appcode.answer",
  "pk": 21
},
{
  "fields": {
    "answer": "Sound of Music",
    "comment": "How do you solve a problem like Maria?",
    "protip": "",
    "redirect_url_if_no_new_question": "",
    "old_question": 7,
    "new_question": 8
  },
  "model": "appcode.answer",
  "pk": 22
},
{
  "fields": {
    "answer": "James Bond 007: Goldfinger",
    "comment": "Perhaps you'd also like a Martini? Shaken, not stirred. ",
    "protip": "",
    "redirect_url_if_no_new_question": "",
    "old_question": 7,
    "new_question": 8
  },
  "model": "appcode.answer",
  "pk": 23
},
{
  "fields": {
    "answer": "Casablanca",
    "comment": "Here's looking at you, kid.",
    "protip": "",
    "redirect_url_if_no_new_question": "",
    "old_question": 7,
    "new_question": 8
  },
  "model": "appcode.answer",
  "pk": 24
},
{
  "fields": {
    "answer": "Yellow Submarine",
    "comment": "I've heard the Octupus's Garden is particularly lovely",
    "protip": "",
    "redirect_url_if_no_new_question": "",
    "old_question": 7,
    "new_question": 8
  },
  "model": "appcode.answer",
  "pk": 25
},
{
  "fields": {
    "answer": "A documentary about Bach",
    "comment": "Do you really need this survey? Just buy your season tickets already.",
    "protip": "",
    "redirect_url_if_no_new_question": "",
    "old_question": 7,
    "new_question": 8
  },
  "model": "appcode.answer",
  "pk": 26
},
{
  "fields": {
    "answer": "The Lion King",
    "comment": "Can you feel the love tonight?",
    "protip": "",
    "redirect_url_if_no_new_question": "",
    "old_question": 7,
    "new_question": 8
  },
  "model": "appcode.answer",
  "pk": 27
},
{
  "fields": {
    "answer": "Entertain me",
    "comment": "",
    "protip": "",
    "redirect_url_if_no_new_question": "",
    "old_question": 8,
    "new_question": 666
  },
  "model": "appcode.answer",
  "pk": 28
},
{
  "fields": {
    "answer": "I want the feelz",
    "comment": "",
    "protip": "",
    "redirect_url_if_no_new_question": "",
    "old_question": 8,
    "new_question": 666
  },
  "model": "appcode.answer",
  "pk": 29
},
{
  "fields": {
    "answer": "The composer(s) and their stories",
    "comment": "",
    "protip": "",
    "redirect_url_if_no_new_question": "",
    "old_question": 10,
    "new_question": 11
  },
  "model": "appcode.answer",
  "pk": 30
},
{
  "fields": {
    "answer": "The musicians and their instruments",
    "comment": "",
    "protip": "",
    "redirect_url_if_no_new_question": "",
    "old_question": 10,
    "new_question": 666
  },
  "model": "appcode.answer",
  "pk": 31
},
{
  "fields": {
    "answer": "The venue",
    "comment": "",
    "protip": "",
    "redirect_url_if_no_new_question": "",
    "old_question": 10,
    "new_question": 12
  },
  "model": "appcode.answer",
  "pk": 32
},
{
  "fields": {
    "answer": "Parking",
    "comment": "",
    "protip": "",
    "redirect_url_if_no_new_question": "",
    "old_question": 10,
    "new_question": 666
  },
  "model": "appcode.answer",
  "pk": 33
},
{
  "fields": {
    "answer": "Beethoven Marathon",
    "comment": "\"I like your opera. I think I will set it to music\"  This is what a Beethoven burn sounds like.",
    "protip": "",
    "redirect_url_if_no_new_question": "",
    "old_question": 11,
    "new_question": 666
  },
  "model": "appcode.answer",
  "pk": 34
},
{
  "fields": {
    "answer": "Sgt. Pepper",
    "comment": "Fun Fact: The Beatles spent 700 hours recording Sgt. Pepper (In contrast, they spent 10 hours on their first album, Please Please Me)",
    "protip": "",
    "redirect_url_if_no_new_question": "",
    "old_question": 11,
    "new_question": 666
  },
  "model": "appcode.answer",
  "pk": 35
},
{
  "fields": {
    "answer": "Front row",
    "comment": "There's really not a bad seat in the house",
    "protip": "",
    "redirect_url_if_no_new_question": "",
    "old_question": 12,
    "new_question": 666
  },
  "model": "appcode.answer",
  "pk": 36
},
{
  "fields": {
    "answer": "In the middle half way up",
    "comment": "There's really not a bad seat in the house",
    "protip": "",
    "redirect_url_if_no_new_question": "",
    "old_question": 12,
    "new_question": 666
  },
  "model": "appcode.answer",
  "pk": 37
},
{
  "fields": {
    "answer": "The top left corner of the mezzanine",
    "comment": "There's really not a bad seat in the house",
    "protip": "",
    "redirect_url_if_no_new_question": "",
    "old_question": 12,
    "new_question": 666
  },
  "model": "appcode.answer",
  "pk": 38
},
{
  "fields": {
    "answer": "Relaxing after a long week",
    "comment": "",
    "protip": "",
    "redirect_url_if_no_new_question": "",
    "old_question": 3,
    "new_question": 5
  },
  "model": "appcode.answer",
  "pk": 39
},
{
  "fields": {
    "description": "Classical popera group Tenore combine their stunning vocal talents with the musical stylings of the KWS for this exquisite concert. Tenore has won prestigious awards and wowed communities with their timeless, beautiful music with hits like You Raise Me Up, Fare Thee Well and Nessun Dorma. Known for powerhouse vocals, inspiring music and audience participation, this concert is sure to delight KWS audiences!",
    "title": "Tenore",
    "highlights": "",
    "image": "http://www.kwsymphony.ca/2015_16/subscription/pops-banner.jpg",
    "date": "2015-08-25",
    "youtube_embed_link": null
  },
  "model": "appcode.concert",
  "pk": 1
},
{
  "fields": {
    "description": "Bond\u2026 James Bond. Experience the drama and mystery of the iconic spy with a tribute to the music of James Bond. Hear music from 007\u2019s most thrilling missions with classic Bond theme songs and essentials from Dr. No, Live and Let Die, For Your Eyes Only and recent Oscar\u00ae winner, Skyfall, featuring the vocals of Broadway stars Capathia Jenkins and Ron Bohmer.",
    "title": "James Bond: The Music",
    "highlights": "",
    "image": "http://kwsymphony.ca/2015_16/subscription/pops-banner.jpg",
    "date": "2015-10-09",
    "youtube_embed_link": null
  },
  "model": "appcode.concert",
  "pk": 2
},
{
  "fields": {
    "description": "Yuletide Spectacular is back with an all-new program featuring The Hockey Sweater.\r\nThe classic short story by Canadian author Roch Carrier has been interpreted for orchestra by Canadian composer Abigail Richardson, together with stunning visuals of the original illustrations from the book. The celebration continues with special guests from the community joining the KWS to play your holiday favourites. Together with the everpopular carol sing-along, this is a spectacularly festive concert!",
    "title": "Yuletide Spectacular",
    "highlights": "",
    "image": "http://kwsymphony.ca/2015_16/subscription/pops-banner.jpg",
    "date": "2015-12-18",
    "youtube_embed_link": null
  },
  "model": "appcode.concert",
  "pk": 3
},
{
  "fields": {
    "description": "Relive the beloved Beatles\u2019 album Sgt. Pepper\u2019s Lonely Hearts Club Band with Canada\u2019s Art of Time Ensemble and the KWS. Made up of Canadian pop icons, including Craig Northey and Glen Phillips of popular 90s bands Odds and Toad the Wet Sprocket, and Andy Maize of the enduring roots rock band Skydiggers, Art of Time Ensemble re-imagines and re-invents Sgt. Pepper through arrangements from pop, jazz and classical composers, bringing a unique perspective and orchestral arrangements to this classic album.",
    "title": "Sgt. Pepper's Lonely Hearts Club Band",
    "highlights": "",
    "image": "http://kwsymphony.ca/2015_16/subscription/pops-banner.jpg",
    "date": "2015-05-22",
    "youtube_embed_link": null
  },
  "model": "appcode.concert",
  "pk": 4
},
{
  "fields": {
    "description": "One of Canada\u2019s most beloved male vocalists and crooner in the style of Sinatra, Matt Dusk, and the angelic songstress and triple East Coast Music Award nominee, Eleanor McCain, join the KWS for a concert of familiar classic and contemporary love songs. Featuring selections from McCain\u2019s new album Runaway, produced by Matt Dusk, the two pair up for the poignant duet To Make You Feel My Love and other symphonic love songs. Join the KWS to celebrate love with lush, elegant music for the eternal romantic. A perfect start to your Valentine\u2019s Day celebration!",
    "title": "Matt Dusk & Eleanor McCain: The Music of Love",
    "highlights": "",
    "image": "http://kwsymphony.ca/2015_16/subscription/pops-banner.jpg",
    "date": "2016-02-12",
    "youtube_embed_link": null
  },
  "model": "appcode.concert",
  "pk": 5
},
{
  "fields": {
    "description": "KWS favourite Matt Catingub returns to conduct this energetic concert featuring dance music spanning 70 years from swing to hip hop! From Glenn Miller\u2019s big band classic In the Mood, to the early days of Rock \u2018n Roll with hits like Bill Haley\u2019s Rock Around the Clock and the Beatles\u2019 Twist and Shout, to the disco era and the 80s with Madonna\u2019s Vogue, there is something for all ages. Featuring drummer Steve Moretti and vocalist Anita Hall, this concert is sure to have you dancing in the aisles!",
    "title": "Dancin' Thru The Decades",
    "highlights": "",
    "image": "http://kwsymphony.ca/2015_16/subscription/pops-banner.jpg",
    "date": "2015-05-11",
    "youtube_embed_link": null
  },
  "model": "appcode.concert",
  "pk": 6
},
{
  "fields": {
    "description": "The great-grandchildren of Captain and Maria von Trapp, made famous by the beloved 1965 film, The Sound of Music, bring a new generation of voices to the legendary family tradition. Inspired by Austrian and American folk songs, this vocal quartet brings modern flair to classics like Edelweiss and Dream A Little Dream of Me, together with songs from their original new release Dancing in Gold, accompanied by the KWS led by Music Director Edwin Outwater!",
    "title": "The Von Trapps",
    "highlights": "",
    "image": "http://kwsymphony.ca/2015_16/subscription/pops-banner.jpg",
    "date": "2016-04-15",
    "youtube_embed_link": null
  },
  "model": "appcode.concert",
  "pk": 7
},
{
  "fields": {
    "description": "Guest Conductor Lucas Waldin returns to the KWS to lead a very special program to celebrate the 70th anniversary season. With a number of guest artists back by popular demand, including the Carousel Dance Company, The Grand Philharmonic Youth Choir and the Waterloo Regional Police Male Chorus, this concert will be curated by you, the audience!\r\n\r\nVisit kwsymphony.ca/KWSByRequest and fill out the survey by June 1, 2015. Your favourite selections could be included in this evening of music from stage, screen and concert hall. Don\u2019t miss what is sure to be a delightfully surprising evening celebrating you \u2014 the KWS audience!",
    "title": "KWS By Request",
    "highlights": "",
    "image": "http://kwsymphony.ca/2015_16/subscription/pops-banner.jpg",
    "date": "2015-05-13",
    "youtube_embed_link": null
  },
  "model": "appcode.concert",
  "pk": 8
},
{
  "fields": {
    "description": "The 70th anniversary season begins with an astounding marathon of music as pianist Stewart Goodyear plays all five Beethoven piano concertos with the KWS. This music is a joy to hear, and the immersive multi-night journey into Beethoven\u2019s masterpieces for piano and orchestra will be unforgettable. (Piano Concerto No. 3 appears on the Matin\u00e9e Series, September 26 at 2:30 pm.)",
    "title": "Beethoven Marathon",
    "highlights": "",
    "image": "https://kwsymphony.ca/2015_16/subscription/signature-banner.jpg",
    "date": "2015-09-25",
    "youtube_embed_link": null
  },
  "model": "appcode.concert",
  "pk": 9
},
{
  "fields": {
    "description": "Join the KWS and special guests to explore a world of symmetry, pattern, and the intimate relationship between mathematics and music, with a focus on the beauty and elegance of geometry and its most passionate apostle, the late Donald Coxeter. Regarded as the greatest geometer of the 20th Century and one of Canada\u2019s mathematical heroes, Coxeter\u2019s influence is far-reaching. In the tradition of \u201cBeethoven and Your Brain,\u201d and \u201cQuantum: Music on the Frontier of Science,\u201d this concert is the latest music/science collaboration in the Intersections Series.",
    "title": "The Geometry of Music: Harold Scott MacDonald Coxeter ",
    "highlights": "",
    "image": "https://kwsymphony.ca/2015_16/subscription/intersections-banner.jpg",
    "date": "2016-04-22",
    "youtube_embed_link": null
  },
  "model": "appcode.concert",
  "pk": 10
},
{
  "fields": {
    "description": "Friedrich II of Prussia (1712-86) was not only King, but also a flute player and composer. The musical establishment of his court, particularly at his summer home at Sanssouci Palace, featured prominent composers C.P.E Bach, Quantz and Benda, and was for a time a centre of German musical life. This concert, curated by KWS bassist Bruce McGillivray, brings together works by composers of this \u201cmusical household,\u201d and features the talents of KWS musicians Thomas Kay, John Helmers and concertmaster B\u00e9n\u00e9dicte Lauzi\u00e8re.",
    "title": "Music at Sanssouci",
    "highlights": "",
    "image": "https://kwsymphony.ca/2015_16/subscription/baroque.jpg",
    "date": "2015-11-11",
    "youtube_embed_link": null
  },
  "model": "appcode.concert",
  "pk": 11
},
{
  "fields": {
    "description": "The harp, trombone and oboe introduce you to three talented bears that sing, dance and cook the perfect porridge for Goldilocks in this delightful version of the classic fairy tale.",
    "title": "Goldilocks and The Three Musical Bears",
    "highlights": "",
    "image": "https://kwsymphony.ca/2015_16/subscription/kinder-banner.jpg",
    "date": "2016-04-09",
    "youtube_embed_link": null
  },
  "model": "appcode.concert",
  "pk": 12
},
{
  "fields": {
    "description": "The KWS Youth Orchestra is featured playing side-by-side with the KWS on the following concerts: Yuletide\r\nSpectacular (Pops Series) and KWS Concerto Celebration (Signature Series).",
    "title": "Youth Orchestra Program",
    "highlights": "",
    "image": "https://kwsymphony.ca/2015_16/subscription/yop-banner.jpg",
    "date": "2015-11-28",
    "youtube_embed_link": null
  },
  "model": "appcode.concert",
  "pk": 13
},
{
  "fields": {
    "description": "Opera returns to Kitchener-Waterloo! In this concert version of Johann Strauss, Jr.\u2019s beloved opera, Die Fledermaus, the KWS joins forces with Wilfrid Laurier University music faculty, host Daniel Isengart and surprise guests to present an evening of glorious melody, great laughs and unforgettable performances. We are thrilled to present opera at the Centre In The Square as part of the 70th anniversary celebrations.",
    "title": "Die Fledermaus: Comic Opera in Concert",
    "highlights": "",
    "image": "https://kwsymphony.ca/2015_16/subscription/signature-banner.jpg",
    "date": "2016-01-15",
    "youtube_embed_link": null
  },
  "model": "appcode.concert",
  "pk": 14
},
{
  "fields": {
    "answer": 2,
    "score": 1,
    "concert": 4
  },
  "model": "appcode.concertanswerscore",
  "pk": 1
},
{
  "fields": {
    "answer": 3,
    "score": 1,
    "concert": 13
  },
  "model": "appcode.concertanswerscore",
  "pk": 2
},
{
  "fields": {
    "answer": 4,
    "score": 1,
    "concert": 1
  },
  "model": "appcode.concertanswerscore",
  "pk": 3
},
{
  "fields": {
    "answer": 4,
    "score": 1,
    "concert": 3
  },
  "model": "appcode.concertanswerscore",
  "pk": 4
},
{
  "fields": {
    "answer": 4,
    "score": 1,
    "concert": 6
  },
  "model": "appcode.concertanswerscore",
  "pk": 5
},
{
  "fields": {
    "answer": 4,
    "score": 1,
    "concert": 10
  },
  "model": "appcode.concertanswerscore",
  "pk": 6
},
{
  "fields": {
    "answer": 5,
    "score": 1,
    "concert": 8
  },
  "model": "appcode.concertanswerscore",
  "pk": 7
},
{
  "fields": {
    "answer": 5,
    "score": 1,
    "concert": 9
  },
  "model": "appcode.concertanswerscore",
  "pk": 8
},
{
  "fields": {
    "answer": 5,
    "score": 1,
    "concert": 11
  },
  "model": "appcode.concertanswerscore",
  "pk": 9
},
{
  "fields": {
    "answer": 5,
    "score": 1,
    "concert": 13
  },
  "model": "appcode.concertanswerscore",
  "pk": 10
},
{
  "fields": {
    "answer": 6,
    "score": -1,
    "concert": 9
  },
  "model": "appcode.concertanswerscore",
  "pk": 11
},
{
  "fields": {
    "answer": 6,
    "score": 1,
    "concert": 10
  },
  "model": "appcode.concertanswerscore",
  "pk": 12
},
{
  "fields": {
    "answer": 6,
    "score": -1,
    "concert": 11
  },
  "model": "appcode.concertanswerscore",
  "pk": 13
},
{
  "fields": {
    "answer": 6,
    "score": -1,
    "concert": 14
  },
  "model": "appcode.concertanswerscore",
  "pk": 14
},
{
  "fields": {
    "answer": 7,
    "score": 1,
    "concert": 1
  },
  "model": "appcode.concertanswerscore",
  "pk": 15
},
{
  "fields": {
    "answer": 7,
    "score": 1,
    "concert": 2
  },
  "model": "appcode.concertanswerscore",
  "pk": 16
},
{
  "fields": {
    "answer": 7,
    "score": 1,
    "concert": 4
  },
  "model": "appcode.concertanswerscore",
  "pk": 17
},
{
  "fields": {
    "answer": 7,
    "score": 1,
    "concert": 6
  },
  "model": "appcode.concertanswerscore",
  "pk": 18
},
{
  "fields": {
    "answer": 7,
    "score": 1,
    "concert": 8
  },
  "model": "appcode.concertanswerscore",
  "pk": 19
},
{
  "fields": {
    "answer": 7,
    "score": 1,
    "concert": 10
  },
  "model": "appcode.concertanswerscore",
  "pk": 20
},
{
  "fields": {
    "answer": 7,
    "score": 1,
    "concert": 14
  },
  "model": "appcode.concertanswerscore",
  "pk": 21
},
{
  "fields": {
    "answer": 8,
    "score": 1,
    "concert": 2
  },
  "model": "appcode.concertanswerscore",
  "pk": 22
},
{
  "fields": {
    "answer": 8,
    "score": 1,
    "concert": 3
  },
  "model": "appcode.concertanswerscore",
  "pk": 23
},
{
  "fields": {
    "answer": 8,
    "score": 1,
    "concert": 4
  },
  "model": "appcode.concertanswerscore",
  "pk": 24
},
{
  "fields": {
    "answer": 8,
    "score": 1,
    "concert": 6
  },
  "model": "appcode.concertanswerscore",
  "pk": 25
},
{
  "fields": {
    "answer": 8,
    "score": 1,
    "concert": 10
  },
  "model": "appcode.concertanswerscore",
  "pk": 26
},
{
  "fields": {
    "answer": 9,
    "score": 1,
    "concert": 1
  },
  "model": "appcode.concertanswerscore",
  "pk": 27
},
{
  "fields": {
    "answer": 9,
    "score": -1,
    "concert": 2
  },
  "model": "appcode.concertanswerscore",
  "pk": 28
},
{
  "fields": {
    "answer": 9,
    "score": 1,
    "concert": 5
  },
  "model": "appcode.concertanswerscore",
  "pk": 29
},
{
  "fields": {
    "answer": 9,
    "score": 2,
    "concert": 7
  },
  "model": "appcode.concertanswerscore",
  "pk": 30
},
{
  "fields": {
    "answer": 9,
    "score": 2,
    "concert": 8
  },
  "model": "appcode.concertanswerscore",
  "pk": 31
},
{
  "fields": {
    "answer": 9,
    "score": 2,
    "concert": 9
  },
  "model": "appcode.concertanswerscore",
  "pk": 32
},
{
  "fields": {
    "answer": 9,
    "score": 1,
    "concert": 10
  },
  "model": "appcode.concertanswerscore",
  "pk": 33
},
{
  "fields": {
    "answer": 9,
    "score": 2,
    "concert": 11
  },
  "model": "appcode.concertanswerscore",
  "pk": 34
},
{
  "fields": {
    "answer": 9,
    "score": 1,
    "concert": 13
  },
  "model": "appcode.concertanswerscore",
  "pk": 35
},
{
  "fields": {
    "answer": 9,
    "score": 2,
    "concert": 14
  },
  "model": "appcode.concertanswerscore",
  "pk": 36
},
{
  "fields": {
    "answer": 10,
    "score": 1,
    "concert": 1
  },
  "model": "appcode.concertanswerscore",
  "pk": 37
},
{
  "fields": {
    "answer": 10,
    "score": 2,
    "concert": 2
  },
  "model": "appcode.concertanswerscore",
  "pk": 38
},
{
  "fields": {
    "answer": 10,
    "score": 1,
    "concert": 4
  },
  "model": "appcode.concertanswerscore",
  "pk": 39
},
{
  "fields": {
    "answer": 10,
    "score": 1,
    "concert": 5
  },
  "model": "appcode.concertanswerscore",
  "pk": 40
},
{
  "fields": {
    "answer": 10,
    "score": 1,
    "concert": 6
  },
  "model": "appcode.concertanswerscore",
  "pk": 41
},
{
  "fields": {
    "answer": 10,
    "score": 1,
    "concert": 8
  },
  "model": "appcode.concertanswerscore",
  "pk": 42
},
{
  "fields": {
    "answer": 10,
    "score": 1,
    "concert": 10
  },
  "model": "appcode.concertanswerscore",
  "pk": 43
},
{
  "fields": {
    "answer": 12,
    "score": 4,
    "concert": 12
  },
  "model": "appcode.concertanswerscore",
  "pk": 44
},
{
  "fields": {
    "answer": 12,
    "score": 1,
    "concert": 13
  },
  "model": "appcode.concertanswerscore",
  "pk": 45
},
{
  "fields": {
    "answer": 13,
    "score": 2,
    "concert": 3
  },
  "model": "appcode.concertanswerscore",
  "pk": 46
},
{
  "fields": {
    "answer": 13,
    "score": 4,
    "concert": 12
  },
  "model": "appcode.concertanswerscore",
  "pk": 47
},
{
  "fields": {
    "answer": 13,
    "score": 1,
    "concert": 13
  },
  "model": "appcode.concertanswerscore",
  "pk": 48
},
{
  "fields": {
    "answer": 14,
    "score": 1,
    "concert": 2
  },
  "model": "appcode.concertanswerscore",
  "pk": 49
},
{
  "fields": {
    "answer": 14,
    "score": 1,
    "concert": 3
  },
  "model": "appcode.concertanswerscore",
  "pk": 50
},
{
  "fields": {
    "answer": 14,
    "score": 1,
    "concert": 6
  },
  "model": "appcode.concertanswerscore",
  "pk": 51
},
{
  "fields": {
    "answer": 14,
    "score": 1,
    "concert": 8
  },
  "model": "appcode.concertanswerscore",
  "pk": 52
},
{
  "fields": {
    "answer": 14,
    "score": 1,
    "concert": 10
  },
  "model": "appcode.concertanswerscore",
  "pk": 53
},
{
  "fields": {
    "answer": 14,
    "score": 1,
    "concert": 11
  },
  "model": "appcode.concertanswerscore",
  "pk": 54
},
{
  "fields": {
    "answer": 14,
    "score": 1,
    "concert": 13
  },
  "model": "appcode.concertanswerscore",
  "pk": 55
},
{
  "fields": {
    "answer": 15,
    "score": 1,
    "concert": 1
  },
  "model": "appcode.concertanswerscore",
  "pk": 56
},
{
  "fields": {
    "answer": 15,
    "score": 1,
    "concert": 2
  },
  "model": "appcode.concertanswerscore",
  "pk": 57
},
{
  "fields": {
    "answer": 15,
    "score": 1,
    "concert": 3
  },
  "model": "appcode.concertanswerscore",
  "pk": 58
},
{
  "fields": {
    "answer": 15,
    "score": 1,
    "concert": 4
  },
  "model": "appcode.concertanswerscore",
  "pk": 59
},
{
  "fields": {
    "answer": 15,
    "score": 1,
    "concert": 6
  },
  "model": "appcode.concertanswerscore",
  "pk": 60
},
{
  "fields": {
    "answer": 15,
    "score": 1,
    "concert": 7
  },
  "model": "appcode.concertanswerscore",
  "pk": 61
},
{
  "fields": {
    "answer": 15,
    "score": 1,
    "concert": 8
  },
  "model": "appcode.concertanswerscore",
  "pk": 62
},
{
  "fields": {
    "answer": 15,
    "score": 2,
    "concert": 10
  },
  "model": "appcode.concertanswerscore",
  "pk": 63
},
{
  "fields": {
    "answer": 15,
    "score": 1,
    "concert": 11
  },
  "model": "appcode.concertanswerscore",
  "pk": 64
},
{
  "fields": {
    "answer": 15,
    "score": 1,
    "concert": 13
  },
  "model": "appcode.concertanswerscore",
  "pk": 65
},
{
  "fields": {
    "answer": 16,
    "score": 1,
    "concert": 8
  },
  "model": "appcode.concertanswerscore",
  "pk": 66
},
{
  "fields": {
    "answer": 16,
    "score": 2,
    "concert": 9
  },
  "model": "appcode.concertanswerscore",
  "pk": 67
},
{
  "fields": {
    "answer": 16,
    "score": 2,
    "concert": 11
  },
  "model": "appcode.concertanswerscore",
  "pk": 68
},
{
  "fields": {
    "answer": 16,
    "score": 1,
    "concert": 13
  },
  "model": "appcode.concertanswerscore",
  "pk": 69
},
{
  "fields": {
    "answer": 16,
    "score": 1,
    "concert": 14
  },
  "model": "appcode.concertanswerscore",
  "pk": 70
},
{
  "fields": {
    "answer": 17,
    "score": 1,
    "concert": 2
  },
  "model": "appcode.concertanswerscore",
  "pk": 71
},
{
  "fields": {
    "answer": 17,
    "score": 1,
    "concert": 4
  },
  "model": "appcode.concertanswerscore",
  "pk": 72
},
{
  "fields": {
    "answer": 17,
    "score": 1,
    "concert": 6
  },
  "model": "appcode.concertanswerscore",
  "pk": 73
},
{
  "fields": {
    "answer": 17,
    "score": -1,
    "concert": 9
  },
  "model": "appcode.concertanswerscore",
  "pk": 74
},
{
  "fields": {
    "answer": 17,
    "score": -1,
    "concert": 11
  },
  "model": "appcode.concertanswerscore",
  "pk": 75
},
{
  "fields": {
    "answer": 17,
    "score": 1,
    "concert": 12
  },
  "model": "appcode.concertanswerscore",
  "pk": 76
},
{
  "fields": {
    "answer": 19,
    "score": 1,
    "concert": 1
  },
  "model": "appcode.concertanswerscore",
  "pk": 77
},
{
  "fields": {
    "answer": 19,
    "score": 1,
    "concert": 5
  },
  "model": "appcode.concertanswerscore",
  "pk": 78
},
{
  "fields": {
    "answer": 19,
    "score": 1,
    "concert": 7
  },
  "model": "appcode.concertanswerscore",
  "pk": 79
},
{
  "fields": {
    "answer": 19,
    "score": 1,
    "concert": 8
  },
  "model": "appcode.concertanswerscore",
  "pk": 80
},
{
  "fields": {
    "answer": 19,
    "score": 1,
    "concert": 9
  },
  "model": "appcode.concertanswerscore",
  "pk": 81
},
{
  "fields": {
    "answer": 19,
    "score": 1,
    "concert": 11
  },
  "model": "appcode.concertanswerscore",
  "pk": 82
},
{
  "fields": {
    "answer": 19,
    "score": 1,
    "concert": 14
  },
  "model": "appcode.concertanswerscore",
  "pk": 83
},
{
  "fields": {
    "answer": 20,
    "score": 1,
    "concert": 8
  },
  "model": "appcode.concertanswerscore",
  "pk": 84
},
{
  "fields": {
    "answer": 20,
    "score": 2,
    "concert": 9
  },
  "model": "appcode.concertanswerscore",
  "pk": 85
},
{
  "fields": {
    "answer": 20,
    "score": 2,
    "concert": 11
  },
  "model": "appcode.concertanswerscore",
  "pk": 86
},
{
  "fields": {
    "answer": 20,
    "score": 1,
    "concert": 13
  },
  "model": "appcode.concertanswerscore",
  "pk": 87
},
{
  "fields": {
    "answer": 20,
    "score": 1,
    "concert": 14
  },
  "model": "appcode.concertanswerscore",
  "pk": 88
},
{
  "fields": {
    "answer": 22,
    "score": 3,
    "concert": 7
  },
  "model": "appcode.concertanswerscore",
  "pk": 89
},
{
  "fields": {
    "answer": 23,
    "score": 3,
    "concert": 2
  },
  "model": "appcode.concertanswerscore",
  "pk": 90
},
{
  "fields": {
    "answer": 24,
    "score": 2,
    "concert": 1
  },
  "model": "appcode.concertanswerscore",
  "pk": 91
},
{
  "fields": {
    "answer": 24,
    "score": 3,
    "concert": 5
  },
  "model": "appcode.concertanswerscore",
  "pk": 92
},
{
  "fields": {
    "answer": 25,
    "score": 3,
    "concert": 4
  },
  "model": "appcode.concertanswerscore",
  "pk": 93
},
{
  "fields": {
    "answer": 26,
    "score": 3,
    "concert": 9
  },
  "model": "appcode.concertanswerscore",
  "pk": 94
},
{
  "fields": {
    "answer": 26,
    "score": 3,
    "concert": 11
  },
  "model": "appcode.concertanswerscore",
  "pk": 95
},
{
  "fields": {
    "answer": 27,
    "score": 2,
    "concert": 3
  },
  "model": "appcode.concertanswerscore",
  "pk": 96
},
{
  "fields": {
    "answer": 27,
    "score": 1,
    "concert": 6
  },
  "model": "appcode.concertanswerscore",
  "pk": 97
},
{
  "fields": {
    "answer": 27,
    "score": 2,
    "concert": 12
  },
  "model": "appcode.concertanswerscore",
  "pk": 98
},
{
  "fields": {
    "answer": 27,
    "score": 1,
    "concert": 13
  },
  "model": "appcode.concertanswerscore",
  "pk": 99
},
{
  "fields": {
    "answer": 28,
    "score": 1,
    "concert": 1
  },
  "model": "appcode.concertanswerscore",
  "pk": 100
},
{
  "fields": {
    "answer": 28,
    "score": 1,
    "concert": 2
  },
  "model": "appcode.concertanswerscore",
  "pk": 101
},
{
  "fields": {
    "answer": 28,
    "score": 1,
    "concert": 3
  },
  "model": "appcode.concertanswerscore",
  "pk": 102
},
{
  "fields": {
    "answer": 28,
    "score": 2,
    "concert": 4
  },
  "model": "appcode.concertanswerscore",
  "pk": 103
},
{
  "fields": {
    "answer": 28,
    "score": 1,
    "concert": 5
  },
  "model": "appcode.concertanswerscore",
  "pk": 104
},
{
  "fields": {
    "answer": 28,
    "score": 2,
    "concert": 6
  },
  "model": "appcode.concertanswerscore",
  "pk": 105
},
{
  "fields": {
    "answer": 28,
    "score": 1,
    "concert": 7
  },
  "model": "appcode.concertanswerscore",
  "pk": 106
},
{
  "fields": {
    "answer": 28,
    "score": 2,
    "concert": 10
  },
  "model": "appcode.concertanswerscore",
  "pk": 107
},
{
  "fields": {
    "answer": 28,
    "score": 1,
    "concert": 13
  },
  "model": "appcode.concertanswerscore",
  "pk": 108
},
{
  "fields": {
    "answer": 29,
    "score": 1,
    "concert": 5
  },
  "model": "appcode.concertanswerscore",
  "pk": 109
},
{
  "fields": {
    "answer": 29,
    "score": 1,
    "concert": 7
  },
  "model": "appcode.concertanswerscore",
  "pk": 110
},
{
  "fields": {
    "answer": 29,
    "score": 2,
    "concert": 9
  },
  "model": "appcode.concertanswerscore",
  "pk": 111
},
{
  "fields": {
    "answer": 29,
    "score": 2,
    "concert": 11
  },
  "model": "appcode.concertanswerscore",
  "pk": 112
},
{
  "fields": {
    "answer": 29,
    "score": 1,
    "concert": 13
  },
  "model": "appcode.concertanswerscore",
  "pk": 113
},
{
  "fields": {
    "answer": 29,
    "score": 1,
    "concert": 14
  },
  "model": "appcode.concertanswerscore",
  "pk": 114
},
{
  "fields": {
    "answer": 1,
    "score": 0,
    "concert": 1
  },
  "model": "appcode.concertanswerscore",
  "pk": 115
},
{
  "fields": {
    "answer": 1,
    "score": 0,
    "concert": 2
  },
  "model": "appcode.concertanswerscore",
  "pk": 116
},
{
  "fields": {
    "answer": 1,
    "score": 0,
    "concert": 3
  },
  "model": "appcode.concertanswerscore",
  "pk": 117
},
{
  "fields": {
    "answer": 1,
    "score": 0,
    "concert": 4
  },
  "model": "appcode.concertanswerscore",
  "pk": 118
},
{
  "fields": {
    "answer": 1,
    "score": 0,
    "concert": 5
  },
  "model": "appcode.concertanswerscore",
  "pk": 119
},
{
  "fields": {
    "answer": 1,
    "score": 0,
    "concert": 6
  },
  "model": "appcode.concertanswerscore",
  "pk": 120
},
{
  "fields": {
    "answer": 1,
    "score": 0,
    "concert": 7
  },
  "model": "appcode.concertanswerscore",
  "pk": 121
},
{
  "fields": {
    "answer": 1,
    "score": 0,
    "concert": 8
  },
  "model": "appcode.concertanswerscore",
  "pk": 122
},
{
  "fields": {
    "answer": 1,
    "score": 0,
    "concert": 9
  },
  "model": "appcode.concertanswerscore",
  "pk": 123
},
{
  "fields": {
    "answer": 1,
    "score": 0,
    "concert": 10
  },
  "model": "appcode.concertanswerscore",
  "pk": 124
},
{
  "fields": {
    "answer": 1,
    "score": 0,
    "concert": 11
  },
  "model": "appcode.concertanswerscore",
  "pk": 125
},
{
  "fields": {
    "answer": 1,
    "score": 0,
    "concert": 12
  },
  "model": "appcode.concertanswerscore",
  "pk": 126
},
{
  "fields": {
    "answer": 1,
    "score": 0,
    "concert": 13
  },
  "model": "appcode.concertanswerscore",
  "pk": 127
},
{
  "fields": {
    "answer": 1,
    "score": 0,
    "concert": 14
  },
  "model": "appcode.concertanswerscore",
  "pk": 128
},
{
  "fields": {
    "answer": 2,
    "score": 0,
    "concert": 1
  },
  "model": "appcode.concertanswerscore",
  "pk": 129
},
{
  "fields": {
    "answer": 2,
    "score": 0,
    "concert": 2
  },
  "model": "appcode.concertanswerscore",
  "pk": 130
},
{
  "fields": {
    "answer": 2,
    "score": 0,
    "concert": 3
  },
  "model": "appcode.concertanswerscore",
  "pk": 131
},
{
  "fields": {
    "answer": 2,
    "score": 0,
    "concert": 5
  },
  "model": "appcode.concertanswerscore",
  "pk": 132
},
{
  "fields": {
    "answer": 2,
    "score": 0,
    "concert": 6
  },
  "model": "appcode.concertanswerscore",
  "pk": 133
},
{
  "fields": {
    "answer": 2,
    "score": 0,
    "concert": 7
  },
  "model": "appcode.concertanswerscore",
  "pk": 134
},
{
  "fields": {
    "answer": 2,
    "score": 0,
    "concert": 8
  },
  "model": "appcode.concertanswerscore",
  "pk": 135
},
{
  "fields": {
    "answer": 2,
    "score": 0,
    "concert": 9
  },
  "model": "appcode.concertanswerscore",
  "pk": 136
},
{
  "fields": {
    "answer": 2,
    "score": 0,
    "concert": 10
  },
  "model": "appcode.concertanswerscore",
  "pk": 137
},
{
  "fields": {
    "answer": 2,
    "score": 0,
    "concert": 11
  },
  "model": "appcode.concertanswerscore",
  "pk": 138
},
{
  "fields": {
    "answer": 2,
    "score": 0,
    "concert": 12
  },
  "model": "appcode.concertanswerscore",
  "pk": 139
},
{
  "fields": {
    "answer": 2,
    "score": 0,
    "concert": 13
  },
  "model": "appcode.concertanswerscore",
  "pk": 140
},
{
  "fields": {
    "answer": 2,
    "score": 0,
    "concert": 14
  },
  "model": "appcode.concertanswerscore",
  "pk": 141
},
{
  "fields": {
    "answer": 3,
    "score": 0,
    "concert": 1
  },
  "model": "appcode.concertanswerscore",
  "pk": 142
},
{
  "fields": {
    "answer": 3,
    "score": 0,
    "concert": 2
  },
  "model": "appcode.concertanswerscore",
  "pk": 143
},
{
  "fields": {
    "answer": 3,
    "score": 0,
    "concert": 3
  },
  "model": "appcode.concertanswerscore",
  "pk": 144
},
{
  "fields": {
    "answer": 3,
    "score": 0,
    "concert": 4
  },
  "model": "appcode.concertanswerscore",
  "pk": 145
},
{
  "fields": {
    "answer": 3,
    "score": 0,
    "concert": 5
  },
  "model": "appcode.concertanswerscore",
  "pk": 146
},
{
  "fields": {
    "answer": 3,
    "score": 0,
    "concert": 6
  },
  "model": "appcode.concertanswerscore",
  "pk": 147
},
{
  "fields": {
    "answer": 3,
    "score": 0,
    "concert": 7
  },
  "model": "appcode.concertanswerscore",
  "pk": 148
},
{
  "fields": {
    "answer": 3,
    "score": 0,
    "concert": 8
  },
  "model": "appcode.concertanswerscore",
  "pk": 149
},
{
  "fields": {
    "answer": 3,
    "score": 0,
    "concert": 9
  },
  "model": "appcode.concertanswerscore",
  "pk": 150
},
{
  "fields": {
    "answer": 3,
    "score": 0,
    "concert": 10
  },
  "model": "appcode.concertanswerscore",
  "pk": 151
},
{
  "fields": {
    "answer": 3,
    "score": 0,
    "concert": 11
  },
  "model": "appcode.concertanswerscore",
  "pk": 152
},
{
  "fields": {
    "answer": 3,
    "score": 0,
    "concert": 12
  },
  "model": "appcode.concertanswerscore",
  "pk": 153
},
{
  "fields": {
    "answer": 3,
    "score": 0,
    "concert": 14
  },
  "model": "appcode.concertanswerscore",
  "pk": 154
},
{
  "fields": {
    "answer": 4,
    "score": 0,
    "concert": 2
  },
  "model": "appcode.concertanswerscore",
  "pk": 155
},
{
  "fields": {
    "answer": 4,
    "score": 0,
    "concert": 4
  },
  "model": "appcode.concertanswerscore",
  "pk": 156
},
{
  "fields": {
    "answer": 4,
    "score": 0,
    "concert": 5
  },
  "model": "appcode.concertanswerscore",
  "pk": 157
},
{
  "fields": {
    "answer": 4,
    "score": 0,
    "concert": 7
  },
  "model": "appcode.concertanswerscore",
  "pk": 158
},
{
  "fields": {
    "answer": 4,
    "score": 0,
    "concert": 8
  },
  "model": "appcode.concertanswerscore",
  "pk": 159
},
{
  "fields": {
    "answer": 4,
    "score": 0,
    "concert": 9
  },
  "model": "appcode.concertanswerscore",
  "pk": 160
},
{
  "fields": {
    "answer": 4,
    "score": 0,
    "concert": 11
  },
  "model": "appcode.concertanswerscore",
  "pk": 161
},
{
  "fields": {
    "answer": 4,
    "score": 0,
    "concert": 12
  },
  "model": "appcode.concertanswerscore",
  "pk": 162
},
{
  "fields": {
    "answer": 4,
    "score": 0,
    "concert": 13
  },
  "model": "appcode.concertanswerscore",
  "pk": 163
},
{
  "fields": {
    "answer": 4,
    "score": 0,
    "concert": 14
  },
  "model": "appcode.concertanswerscore",
  "pk": 164
},
{
  "fields": {
    "answer": 5,
    "score": 0,
    "concert": 1
  },
  "model": "appcode.concertanswerscore",
  "pk": 165
},
{
  "fields": {
    "answer": 5,
    "score": 0,
    "concert": 2
  },
  "model": "appcode.concertanswerscore",
  "pk": 166
},
{
  "fields": {
    "answer": 5,
    "score": 0,
    "concert": 3
  },
  "model": "appcode.concertanswerscore",
  "pk": 167
},
{
  "fields": {
    "answer": 5,
    "score": 0,
    "concert": 4
  },
  "model": "appcode.concertanswerscore",
  "pk": 168
},
{
  "fields": {
    "answer": 5,
    "score": 0,
    "concert": 5
  },
  "model": "appcode.concertanswerscore",
  "pk": 169
},
{
  "fields": {
    "answer": 5,
    "score": 0,
    "concert": 6
  },
  "model": "appcode.concertanswerscore",
  "pk": 170
},
{
  "fields": {
    "answer": 5,
    "score": 0,
    "concert": 7
  },
  "model": "appcode.concertanswerscore",
  "pk": 171
},
{
  "fields": {
    "answer": 5,
    "score": 0,
    "concert": 10
  },
  "model": "appcode.concertanswerscore",
  "pk": 172
},
{
  "fields": {
    "answer": 5,
    "score": 0,
    "concert": 12
  },
  "model": "appcode.concertanswerscore",
  "pk": 173
},
{
  "fields": {
    "answer": 5,
    "score": 0,
    "concert": 14
  },
  "model": "appcode.concertanswerscore",
  "pk": 174
},
{
  "fields": {
    "answer": 6,
    "score": 0,
    "concert": 1
  },
  "model": "appcode.concertanswerscore",
  "pk": 175
},
{
  "fields": {
    "answer": 6,
    "score": 0,
    "concert": 2
  },
  "model": "appcode.concertanswerscore",
  "pk": 176
},
{
  "fields": {
    "answer": 6,
    "score": 0,
    "concert": 3
  },
  "model": "appcode.concertanswerscore",
  "pk": 177
},
{
  "fields": {
    "answer": 6,
    "score": 0,
    "concert": 4
  },
  "model": "appcode.concertanswerscore",
  "pk": 178
},
{
  "fields": {
    "answer": 6,
    "score": 0,
    "concert": 5
  },
  "model": "appcode.concertanswerscore",
  "pk": 179
},
{
  "fields": {
    "answer": 6,
    "score": 0,
    "concert": 6
  },
  "model": "appcode.concertanswerscore",
  "pk": 180
},
{
  "fields": {
    "answer": 6,
    "score": 0,
    "concert": 7
  },
  "model": "appcode.concertanswerscore",
  "pk": 181
},
{
  "fields": {
    "answer": 6,
    "score": 0,
    "concert": 8
  },
  "model": "appcode.concertanswerscore",
  "pk": 182
},
{
  "fields": {
    "answer": 6,
    "score": 0,
    "concert": 12
  },
  "model": "appcode.concertanswerscore",
  "pk": 183
},
{
  "fields": {
    "answer": 6,
    "score": 0,
    "concert": 13
  },
  "model": "appcode.concertanswerscore",
  "pk": 184
},
{
  "fields": {
    "answer": 7,
    "score": 0,
    "concert": 3
  },
  "model": "appcode.concertanswerscore",
  "pk": 185
},
{
  "fields": {
    "answer": 7,
    "score": 0,
    "concert": 5
  },
  "model": "appcode.concertanswerscore",
  "pk": 186
},
{
  "fields": {
    "answer": 7,
    "score": 0,
    "concert": 7
  },
  "model": "appcode.concertanswerscore",
  "pk": 187
},
{
  "fields": {
    "answer": 7,
    "score": 0,
    "concert": 9
  },
  "model": "appcode.concertanswerscore",
  "pk": 188
},
{
  "fields": {
    "answer": 7,
    "score": 0,
    "concert": 11
  },
  "model": "appcode.concertanswerscore",
  "pk": 189
},
{
  "fields": {
    "answer": 7,
    "score": 0,
    "concert": 12
  },
  "model": "appcode.concertanswerscore",
  "pk": 190
},
{
  "fields": {
    "answer": 7,
    "score": 0,
    "concert": 13
  },
  "model": "appcode.concertanswerscore",
  "pk": 191
},
{
  "fields": {
    "answer": 8,
    "score": 0,
    "concert": 1
  },
  "model": "appcode.concertanswerscore",
  "pk": 192
},
{
  "fields": {
    "answer": 8,
    "score": 0,
    "concert": 5
  },
  "model": "appcode.concertanswerscore",
  "pk": 193
},
{
  "fields": {
    "answer": 8,
    "score": 0,
    "concert": 7
  },
  "model": "appcode.concertanswerscore",
  "pk": 194
},
{
  "fields": {
    "answer": 8,
    "score": 0,
    "concert": 8
  },
  "model": "appcode.concertanswerscore",
  "pk": 195
},
{
  "fields": {
    "answer": 8,
    "score": 0,
    "concert": 9
  },
  "model": "appcode.concertanswerscore",
  "pk": 196
},
{
  "fields": {
    "answer": 8,
    "score": 0,
    "concert": 11
  },
  "model": "appcode.concertanswerscore",
  "pk": 197
},
{
  "fields": {
    "answer": 8,
    "score": 0,
    "concert": 12
  },
  "model": "appcode.concertanswerscore",
  "pk": 198
},
{
  "fields": {
    "answer": 8,
    "score": 0,
    "concert": 13
  },
  "model": "appcode.concertanswerscore",
  "pk": 199
},
{
  "fields": {
    "answer": 8,
    "score": 0,
    "concert": 14
  },
  "model": "appcode.concertanswerscore",
  "pk": 200
},
{
  "fields": {
    "answer": 9,
    "score": 0,
    "concert": 3
  },
  "model": "appcode.concertanswerscore",
  "pk": 201
},
{
  "fields": {
    "answer": 9,
    "score": 0,
    "concert": 4
  },
  "model": "appcode.concertanswerscore",
  "pk": 202
},
{
  "fields": {
    "answer": 9,
    "score": 0,
    "concert": 6
  },
  "model": "appcode.concertanswerscore",
  "pk": 203
},
{
  "fields": {
    "answer": 9,
    "score": 0,
    "concert": 12
  },
  "model": "appcode.concertanswerscore",
  "pk": 204
},
{
  "fields": {
    "answer": 10,
    "score": 0,
    "concert": 3
  },
  "model": "appcode.concertanswerscore",
  "pk": 205
},
{
  "fields": {
    "answer": 10,
    "score": 0,
    "concert": 7
  },
  "model": "appcode.concertanswerscore",
  "pk": 206
},
{
  "fields": {
    "answer": 10,
    "score": 0,
    "concert": 9
  },
  "model": "appcode.concertanswerscore",
  "pk": 207
},
{
  "fields": {
    "answer": 10,
    "score": 0,
    "concert": 11
  },
  "model": "appcode.concertanswerscore",
  "pk": 208
},
{
  "fields": {
    "answer": 10,
    "score": 0,
    "concert": 12
  },
  "model": "appcode.concertanswerscore",
  "pk": 209
},
{
  "fields": {
    "answer": 10,
    "score": 0,
    "concert": 13
  },
  "model": "appcode.concertanswerscore",
  "pk": 210
},
{
  "fields": {
    "answer": 10,
    "score": 0,
    "concert": 14
  },
  "model": "appcode.concertanswerscore",
  "pk": 211
},
{
  "fields": {
    "answer": 11,
    "score": 0,
    "concert": 1
  },
  "model": "appcode.concertanswerscore",
  "pk": 212
},
{
  "fields": {
    "answer": 11,
    "score": 0,
    "concert": 2
  },
  "model": "appcode.concertanswerscore",
  "pk": 213
},
{
  "fields": {
    "answer": 11,
    "score": 0,
    "concert": 3
  },
  "model": "appcode.concertanswerscore",
  "pk": 214
},
{
  "fields": {
    "answer": 11,
    "score": 0,
    "concert": 4
  },
  "model": "appcode.concertanswerscore",
  "pk": 215
},
{
  "fields": {
    "answer": 11,
    "score": 0,
    "concert": 5
  },
  "model": "appcode.concertanswerscore",
  "pk": 216
},
{
  "fields": {
    "answer": 11,
    "score": 0,
    "concert": 6
  },
  "model": "appcode.concertanswerscore",
  "pk": 217
},
{
  "fields": {
    "answer": 11,
    "score": 0,
    "concert": 7
  },
  "model": "appcode.concertanswerscore",
  "pk": 218
},
{
  "fields": {
    "answer": 11,
    "score": 0,
    "concert": 8
  },
  "model": "appcode.concertanswerscore",
  "pk": 219
},
{
  "fields": {
    "answer": 11,
    "score": 0,
    "concert": 9
  },
  "model": "appcode.concertanswerscore",
  "pk": 220
},
{
  "fields": {
    "answer": 11,
    "score": 0,
    "concert": 10
  },
  "model": "appcode.concertanswerscore",
  "pk": 221
},
{
  "fields": {
    "answer": 11,
    "score": 0,
    "concert": 11
  },
  "model": "appcode.concertanswerscore",
  "pk": 222
},
{
  "fields": {
    "answer": 11,
    "score": 0,
    "concert": 12
  },
  "model": "appcode.concertanswerscore",
  "pk": 223
},
{
  "fields": {
    "answer": 11,
    "score": 0,
    "concert": 13
  },
  "model": "appcode.concertanswerscore",
  "pk": 224
},
{
  "fields": {
    "answer": 11,
    "score": 0,
    "concert": 14
  },
  "model": "appcode.concertanswerscore",
  "pk": 225
},
{
  "fields": {
    "answer": 12,
    "score": 0,
    "concert": 1
  },
  "model": "appcode.concertanswerscore",
  "pk": 226
},
{
  "fields": {
    "answer": 12,
    "score": 0,
    "concert": 2
  },
  "model": "appcode.concertanswerscore",
  "pk": 227
},
{
  "fields": {
    "answer": 12,
    "score": 0,
    "concert": 3
  },
  "model": "appcode.concertanswerscore",
  "pk": 228
},
{
  "fields": {
    "answer": 12,
    "score": 0,
    "concert": 4
  },
  "model": "appcode.concertanswerscore",
  "pk": 229
},
{
  "fields": {
    "answer": 12,
    "score": 0,
    "concert": 5
  },
  "model": "appcode.concertanswerscore",
  "pk": 230
},
{
  "fields": {
    "answer": 12,
    "score": 0,
    "concert": 6
  },
  "model": "appcode.concertanswerscore",
  "pk": 231
},
{
  "fields": {
    "answer": 12,
    "score": 0,
    "concert": 7
  },
  "model": "appcode.concertanswerscore",
  "pk": 232
},
{
  "fields": {
    "answer": 12,
    "score": 0,
    "concert": 8
  },
  "model": "appcode.concertanswerscore",
  "pk": 233
},
{
  "fields": {
    "answer": 12,
    "score": 0,
    "concert": 9
  },
  "model": "appcode.concertanswerscore",
  "pk": 234
},
{
  "fields": {
    "answer": 12,
    "score": 0,
    "concert": 10
  },
  "model": "appcode.concertanswerscore",
  "pk": 235
},
{
  "fields": {
    "answer": 12,
    "score": 0,
    "concert": 11
  },
  "model": "appcode.concertanswerscore",
  "pk": 236
},
{
  "fields": {
    "answer": 12,
    "score": 0,
    "concert": 14
  },
  "model": "appcode.concertanswerscore",
  "pk": 237
},
{
  "fields": {
    "answer": 13,
    "score": 0,
    "concert": 1
  },
  "model": "appcode.concertanswerscore",
  "pk": 238
},
{
  "fields": {
    "answer": 13,
    "score": 0,
    "concert": 2
  },
  "model": "appcode.concertanswerscore",
  "pk": 239
},
{
  "fields": {
    "answer": 13,
    "score": 0,
    "concert": 4
  },
  "model": "appcode.concertanswerscore",
  "pk": 240
},
{
  "fields": {
    "answer": 13,
    "score": 0,
    "concert": 5
  },
  "model": "appcode.concertanswerscore",
  "pk": 241
},
{
  "fields": {
    "answer": 13,
    "score": 0,
    "concert": 6
  },
  "model": "appcode.concertanswerscore",
  "pk": 242
},
{
  "fields": {
    "answer": 13,
    "score": 0,
    "concert": 7
  },
  "model": "appcode.concertanswerscore",
  "pk": 243
},
{
  "fields": {
    "answer": 13,
    "score": 0,
    "concert": 8
  },
  "model": "appcode.concertanswerscore",
  "pk": 244
},
{
  "fields": {
    "answer": 13,
    "score": 0,
    "concert": 9
  },
  "model": "appcode.concertanswerscore",
  "pk": 245
},
{
  "fields": {
    "answer": 13,
    "score": 0,
    "concert": 10
  },
  "model": "appcode.concertanswerscore",
  "pk": 246
},
{
  "fields": {
    "answer": 13,
    "score": 0,
    "concert": 11
  },
  "model": "appcode.concertanswerscore",
  "pk": 247
},
{
  "fields": {
    "answer": 13,
    "score": 0,
    "concert": 14
  },
  "model": "appcode.concertanswerscore",
  "pk": 248
},
{
  "fields": {
    "answer": 14,
    "score": 0,
    "concert": 1
  },
  "model": "appcode.concertanswerscore",
  "pk": 249
},
{
  "fields": {
    "answer": 14,
    "score": 0,
    "concert": 4
  },
  "model": "appcode.concertanswerscore",
  "pk": 250
},
{
  "fields": {
    "answer": 14,
    "score": 0,
    "concert": 5
  },
  "model": "appcode.concertanswerscore",
  "pk": 251
},
{
  "fields": {
    "answer": 14,
    "score": 0,
    "concert": 7
  },
  "model": "appcode.concertanswerscore",
  "pk": 252
},
{
  "fields": {
    "answer": 14,
    "score": 0,
    "concert": 9
  },
  "model": "appcode.concertanswerscore",
  "pk": 253
},
{
  "fields": {
    "answer": 14,
    "score": 0,
    "concert": 12
  },
  "model": "appcode.concertanswerscore",
  "pk": 254
},
{
  "fields": {
    "answer": 14,
    "score": 0,
    "concert": 14
  },
  "model": "appcode.concertanswerscore",
  "pk": 255
},
{
  "fields": {
    "answer": 15,
    "score": 0,
    "concert": 5
  },
  "model": "appcode.concertanswerscore",
  "pk": 256
},
{
  "fields": {
    "answer": 15,
    "score": 0,
    "concert": 9
  },
  "model": "appcode.concertanswerscore",
  "pk": 257
},
{
  "fields": {
    "answer": 15,
    "score": 0,
    "concert": 12
  },
  "model": "appcode.concertanswerscore",
  "pk": 258
},
{
  "fields": {
    "answer": 15,
    "score": 0,
    "concert": 14
  },
  "model": "appcode.concertanswerscore",
  "pk": 259
},
{
  "fields": {
    "answer": 16,
    "score": 0,
    "concert": 1
  },
  "model": "appcode.concertanswerscore",
  "pk": 260
},
{
  "fields": {
    "answer": 16,
    "score": 0,
    "concert": 2
  },
  "model": "appcode.concertanswerscore",
  "pk": 261
},
{
  "fields": {
    "answer": 16,
    "score": 0,
    "concert": 3
  },
  "model": "appcode.concertanswerscore",
  "pk": 262
},
{
  "fields": {
    "answer": 16,
    "score": 0,
    "concert": 4
  },
  "model": "appcode.concertanswerscore",
  "pk": 263
},
{
  "fields": {
    "answer": 16,
    "score": 0,
    "concert": 5
  },
  "model": "appcode.concertanswerscore",
  "pk": 264
},
{
  "fields": {
    "answer": 16,
    "score": 0,
    "concert": 6
  },
  "model": "appcode.concertanswerscore",
  "pk": 265
},
{
  "fields": {
    "answer": 16,
    "score": 0,
    "concert": 7
  },
  "model": "appcode.concertanswerscore",
  "pk": 266
},
{
  "fields": {
    "answer": 16,
    "score": 0,
    "concert": 10
  },
  "model": "appcode.concertanswerscore",
  "pk": 267
},
{
  "fields": {
    "answer": 16,
    "score": 0,
    "concert": 12
  },
  "model": "appcode.concertanswerscore",
  "pk": 268
},
{
  "fields": {
    "answer": 17,
    "score": 0,
    "concert": 1
  },
  "model": "appcode.concertanswerscore",
  "pk": 269
},
{
  "fields": {
    "answer": 17,
    "score": 0,
    "concert": 3
  },
  "model": "appcode.concertanswerscore",
  "pk": 270
},
{
  "fields": {
    "answer": 17,
    "score": 0,
    "concert": 5
  },
  "model": "appcode.concertanswerscore",
  "pk": 271
},
{
  "fields": {
    "answer": 17,
    "score": 0,
    "concert": 7
  },
  "model": "appcode.concertanswerscore",
  "pk": 272
},
{
  "fields": {
    "answer": 17,
    "score": 0,
    "concert": 8
  },
  "model": "appcode.concertanswerscore",
  "pk": 273
},
{
  "fields": {
    "answer": 17,
    "score": 0,
    "concert": 10
  },
  "model": "appcode.concertanswerscore",
  "pk": 274
},
{
  "fields": {
    "answer": 17,
    "score": 0,
    "concert": 13
  },
  "model": "appcode.concertanswerscore",
  "pk": 275
},
{
  "fields": {
    "answer": 17,
    "score": 0,
    "concert": 14
  },
  "model": "appcode.concertanswerscore",
  "pk": 276
},
{
  "fields": {
    "answer": 18,
    "score": 0,
    "concert": 1
  },
  "model": "appcode.concertanswerscore",
  "pk": 277
},
{
  "fields": {
    "answer": 18,
    "score": 0,
    "concert": 2
  },
  "model": "appcode.concertanswerscore",
  "pk": 278
},
{
  "fields": {
    "answer": 18,
    "score": 0,
    "concert": 3
  },
  "model": "appcode.concertanswerscore",
  "pk": 279
},
{
  "fields": {
    "answer": 18,
    "score": 0,
    "concert": 4
  },
  "model": "appcode.concertanswerscore",
  "pk": 280
},
{
  "fields": {
    "answer": 18,
    "score": 0,
    "concert": 5
  },
  "model": "appcode.concertanswerscore",
  "pk": 281
},
{
  "fields": {
    "answer": 18,
    "score": 0,
    "concert": 6
  },
  "model": "appcode.concertanswerscore",
  "pk": 282
},
{
  "fields": {
    "answer": 18,
    "score": 0,
    "concert": 7
  },
  "model": "appcode.concertanswerscore",
  "pk": 283
},
{
  "fields": {
    "answer": 18,
    "score": 0,
    "concert": 8
  },
  "model": "appcode.concertanswerscore",
  "pk": 284
},
{
  "fields": {
    "answer": 18,
    "score": 0,
    "concert": 9
  },
  "model": "appcode.concertanswerscore",
  "pk": 285
},
{
  "fields": {
    "answer": 18,
    "score": 0,
    "concert": 10
  },
  "model": "appcode.concertanswerscore",
  "pk": 286
},
{
  "fields": {
    "answer": 18,
    "score": 0,
    "concert": 11
  },
  "model": "appcode.concertanswerscore",
  "pk": 287
},
{
  "fields": {
    "answer": 18,
    "score": 0,
    "concert": 12
  },
  "model": "appcode.concertanswerscore",
  "pk": 288
},
{
  "fields": {
    "answer": 18,
    "score": 0,
    "concert": 13
  },
  "model": "appcode.concertanswerscore",
  "pk": 289
},
{
  "fields": {
    "answer": 18,
    "score": 0,
    "concert": 14
  },
  "model": "appcode.concertanswerscore",
  "pk": 290
},
{
  "fields": {
    "answer": 19,
    "score": 0,
    "concert": 2
  },
  "model": "appcode.concertanswerscore",
  "pk": 291
},
{
  "fields": {
    "answer": 19,
    "score": 0,
    "concert": 3
  },
  "model": "appcode.concertanswerscore",
  "pk": 292
},
{
  "fields": {
    "answer": 19,
    "score": 0,
    "concert": 4
  },
  "model": "appcode.concertanswerscore",
  "pk": 293
},
{
  "fields": {
    "answer": 19,
    "score": 0,
    "concert": 6
  },
  "model": "appcode.concertanswerscore",
  "pk": 294
},
{
  "fields": {
    "answer": 19,
    "score": 0,
    "concert": 10
  },
  "model": "appcode.concertanswerscore",
  "pk": 295
},
{
  "fields": {
    "answer": 19,
    "score": 0,
    "concert": 12
  },
  "model": "appcode.concertanswerscore",
  "pk": 296
},
{
  "fields": {
    "answer": 19,
    "score": 0,
    "concert": 13
  },
  "model": "appcode.concertanswerscore",
  "pk": 297
},
{
  "fields": {
    "answer": 20,
    "score": 0,
    "concert": 1
  },
  "model": "appcode.concertanswerscore",
  "pk": 298
},
{
  "fields": {
    "answer": 20,
    "score": 0,
    "concert": 2
  },
  "model": "appcode.concertanswerscore",
  "pk": 299
},
{
  "fields": {
    "answer": 20,
    "score": 0,
    "concert": 3
  },
  "model": "appcode.concertanswerscore",
  "pk": 300
},
{
  "fields": {
    "answer": 20,
    "score": 0,
    "concert": 4
  },
  "model": "appcode.concertanswerscore",
  "pk": 301
},
{
  "fields": {
    "answer": 20,
    "score": 0,
    "concert": 5
  },
  "model": "appcode.concertanswerscore",
  "pk": 302
},
{
  "fields": {
    "answer": 20,
    "score": 0,
    "concert": 6
  },
  "model": "appcode.concertanswerscore",
  "pk": 303
},
{
  "fields": {
    "answer": 20,
    "score": 0,
    "concert": 7
  },
  "model": "appcode.concertanswerscore",
  "pk": 304
},
{
  "fields": {
    "answer": 20,
    "score": 0,
    "concert": 10
  },
  "model": "appcode.concertanswerscore",
  "pk": 305
},
{
  "fields": {
    "answer": 20,
    "score": 0,
    "concert": 12
  },
  "model": "appcode.concertanswerscore",
  "pk": 306
},
{
  "fields": {
    "answer": 21,
    "score": 0,
    "concert": 1
  },
  "model": "appcode.concertanswerscore",
  "pk": 307
},
{
  "fields": {
    "answer": 21,
    "score": 0,
    "concert": 2
  },
  "model": "appcode.concertanswerscore",
  "pk": 308
},
{
  "fields": {
    "answer": 21,
    "score": 0,
    "concert": 3
  },
  "model": "appcode.concertanswerscore",
  "pk": 309
},
{
  "fields": {
    "answer": 21,
    "score": 0,
    "concert": 4
  },
  "model": "appcode.concertanswerscore",
  "pk": 310
},
{
  "fields": {
    "answer": 21,
    "score": 0,
    "concert": 5
  },
  "model": "appcode.concertanswerscore",
  "pk": 311
},
{
  "fields": {
    "answer": 21,
    "score": 0,
    "concert": 6
  },
  "model": "appcode.concertanswerscore",
  "pk": 312
},
{
  "fields": {
    "answer": 21,
    "score": 0,
    "concert": 7
  },
  "model": "appcode.concertanswerscore",
  "pk": 313
},
{
  "fields": {
    "answer": 21,
    "score": 0,
    "concert": 8
  },
  "model": "appcode.concertanswerscore",
  "pk": 314
},
{
  "fields": {
    "answer": 21,
    "score": 0,
    "concert": 9
  },
  "model": "appcode.concertanswerscore",
  "pk": 315
},
{
  "fields": {
    "answer": 21,
    "score": 0,
    "concert": 10
  },
  "model": "appcode.concertanswerscore",
  "pk": 316
},
{
  "fields": {
    "answer": 21,
    "score": 0,
    "concert": 11
  },
  "model": "appcode.concertanswerscore",
  "pk": 317
},
{
  "fields": {
    "answer": 21,
    "score": 0,
    "concert": 12
  },
  "model": "appcode.concertanswerscore",
  "pk": 318
},
{
  "fields": {
    "answer": 21,
    "score": 0,
    "concert": 13
  },
  "model": "appcode.concertanswerscore",
  "pk": 319
},
{
  "fields": {
    "answer": 21,
    "score": 0,
    "concert": 14
  },
  "model": "appcode.concertanswerscore",
  "pk": 320
},
{
  "fields": {
    "answer": 22,
    "score": 0,
    "concert": 1
  },
  "model": "appcode.concertanswerscore",
  "pk": 321
},
{
  "fields": {
    "answer": 22,
    "score": 0,
    "concert": 2
  },
  "model": "appcode.concertanswerscore",
  "pk": 322
},
{
  "fields": {
    "answer": 22,
    "score": 0,
    "concert": 3
  },
  "model": "appcode.concertanswerscore",
  "pk": 323
},
{
  "fields": {
    "answer": 22,
    "score": 0,
    "concert": 4
  },
  "model": "appcode.concertanswerscore",
  "pk": 324
},
{
  "fields": {
    "answer": 22,
    "score": 0,
    "concert": 5
  },
  "model": "appcode.concertanswerscore",
  "pk": 325
},
{
  "fields": {
    "answer": 22,
    "score": 0,
    "concert": 6
  },
  "model": "appcode.concertanswerscore",
  "pk": 326
},
{
  "fields": {
    "answer": 22,
    "score": 0,
    "concert": 8
  },
  "model": "appcode.concertanswerscore",
  "pk": 327
},
{
  "fields": {
    "answer": 22,
    "score": 0,
    "concert": 9
  },
  "model": "appcode.concertanswerscore",
  "pk": 328
},
{
  "fields": {
    "answer": 22,
    "score": 0,
    "concert": 10
  },
  "model": "appcode.concertanswerscore",
  "pk": 329
},
{
  "fields": {
    "answer": 22,
    "score": 0,
    "concert": 11
  },
  "model": "appcode.concertanswerscore",
  "pk": 330
},
{
  "fields": {
    "answer": 22,
    "score": 0,
    "concert": 12
  },
  "model": "appcode.concertanswerscore",
  "pk": 331
},
{
  "fields": {
    "answer": 22,
    "score": 0,
    "concert": 13
  },
  "model": "appcode.concertanswerscore",
  "pk": 332
},
{
  "fields": {
    "answer": 22,
    "score": 0,
    "concert": 14
  },
  "model": "appcode.concertanswerscore",
  "pk": 333
},
{
  "fields": {
    "answer": 23,
    "score": 0,
    "concert": 1
  },
  "model": "appcode.concertanswerscore",
  "pk": 334
},
{
  "fields": {
    "answer": 23,
    "score": 0,
    "concert": 3
  },
  "model": "appcode.concertanswerscore",
  "pk": 335
},
{
  "fields": {
    "answer": 23,
    "score": 0,
    "concert": 4
  },
  "model": "appcode.concertanswerscore",
  "pk": 336
},
{
  "fields": {
    "answer": 23,
    "score": 0,
    "concert": 5
  },
  "model": "appcode.concertanswerscore",
  "pk": 337
},
{
  "fields": {
    "answer": 23,
    "score": 0,
    "concert": 6
  },
  "model": "appcode.concertanswerscore",
  "pk": 338
},
{
  "fields": {
    "answer": 23,
    "score": 0,
    "concert": 7
  },
  "model": "appcode.concertanswerscore",
  "pk": 339
},
{
  "fields": {
    "answer": 23,
    "score": 0,
    "concert": 8
  },
  "model": "appcode.concertanswerscore",
  "pk": 340
},
{
  "fields": {
    "answer": 23,
    "score": 0,
    "concert": 9
  },
  "model": "appcode.concertanswerscore",
  "pk": 341
},
{
  "fields": {
    "answer": 23,
    "score": 0,
    "concert": 10
  },
  "model": "appcode.concertanswerscore",
  "pk": 342
},
{
  "fields": {
    "answer": 23,
    "score": 0,
    "concert": 11
  },
  "model": "appcode.concertanswerscore",
  "pk": 343
},
{
  "fields": {
    "answer": 23,
    "score": 0,
    "concert": 12
  },
  "model": "appcode.concertanswerscore",
  "pk": 344
},
{
  "fields": {
    "answer": 23,
    "score": 0,
    "concert": 13
  },
  "model": "appcode.concertanswerscore",
  "pk": 345
},
{
  "fields": {
    "answer": 23,
    "score": 0,
    "concert": 14
  },
  "model": "appcode.concertanswerscore",
  "pk": 346
},
{
  "fields": {
    "answer": 24,
    "score": 0,
    "concert": 2
  },
  "model": "appcode.concertanswerscore",
  "pk": 347
},
{
  "fields": {
    "answer": 24,
    "score": 0,
    "concert": 3
  },
  "model": "appcode.concertanswerscore",
  "pk": 348
},
{
  "fields": {
    "answer": 24,
    "score": 0,
    "concert": 4
  },
  "model": "appcode.concertanswerscore",
  "pk": 349
},
{
  "fields": {
    "answer": 24,
    "score": 0,
    "concert": 6
  },
  "model": "appcode.concertanswerscore",
  "pk": 350
},
{
  "fields": {
    "answer": 24,
    "score": 0,
    "concert": 7
  },
  "model": "appcode.concertanswerscore",
  "pk": 351
},
{
  "fields": {
    "answer": 24,
    "score": 0,
    "concert": 8
  },
  "model": "appcode.concertanswerscore",
  "pk": 352
},
{
  "fields": {
    "answer": 24,
    "score": 0,
    "concert": 9
  },
  "model": "appcode.concertanswerscore",
  "pk": 353
},
{
  "fields": {
    "answer": 24,
    "score": 0,
    "concert": 10
  },
  "model": "appcode.concertanswerscore",
  "pk": 354
},
{
  "fields": {
    "answer": 24,
    "score": 0,
    "concert": 11
  },
  "model": "appcode.concertanswerscore",
  "pk": 355
},
{
  "fields": {
    "answer": 24,
    "score": 0,
    "concert": 12
  },
  "model": "appcode.concertanswerscore",
  "pk": 356
},
{
  "fields": {
    "answer": 24,
    "score": 0,
    "concert": 13
  },
  "model": "appcode.concertanswerscore",
  "pk": 357
},
{
  "fields": {
    "answer": 24,
    "score": 0,
    "concert": 14
  },
  "model": "appcode.concertanswerscore",
  "pk": 358
},
{
  "fields": {
    "answer": 25,
    "score": 0,
    "concert": 1
  },
  "model": "appcode.concertanswerscore",
  "pk": 359
},
{
  "fields": {
    "answer": 25,
    "score": 0,
    "concert": 2
  },
  "model": "appcode.concertanswerscore",
  "pk": 360
},
{
  "fields": {
    "answer": 25,
    "score": 0,
    "concert": 3
  },
  "model": "appcode.concertanswerscore",
  "pk": 361
},
{
  "fields": {
    "answer": 25,
    "score": 0,
    "concert": 5
  },
  "model": "appcode.concertanswerscore",
  "pk": 362
},
{
  "fields": {
    "answer": 25,
    "score": 0,
    "concert": 6
  },
  "model": "appcode.concertanswerscore",
  "pk": 363
},
{
  "fields": {
    "answer": 25,
    "score": 0,
    "concert": 7
  },
  "model": "appcode.concertanswerscore",
  "pk": 364
},
{
  "fields": {
    "answer": 25,
    "score": 0,
    "concert": 8
  },
  "model": "appcode.concertanswerscore",
  "pk": 365
},
{
  "fields": {
    "answer": 25,
    "score": 0,
    "concert": 9
  },
  "model": "appcode.concertanswerscore",
  "pk": 366
},
{
  "fields": {
    "answer": 25,
    "score": 0,
    "concert": 10
  },
  "model": "appcode.concertanswerscore",
  "pk": 367
},
{
  "fields": {
    "answer": 25,
    "score": 0,
    "concert": 11
  },
  "model": "appcode.concertanswerscore",
  "pk": 368
},
{
  "fields": {
    "answer": 25,
    "score": 0,
    "concert": 12
  },
  "model": "appcode.concertanswerscore",
  "pk": 369
},
{
  "fields": {
    "answer": 25,
    "score": 0,
    "concert": 13
  },
  "model": "appcode.concertanswerscore",
  "pk": 370
},
{
  "fields": {
    "answer": 25,
    "score": 0,
    "concert": 14
  },
  "model": "appcode.concertanswerscore",
  "pk": 371
},
{
  "fields": {
    "answer": 26,
    "score": 0,
    "concert": 1
  },
  "model": "appcode.concertanswerscore",
  "pk": 372
},
{
  "fields": {
    "answer": 26,
    "score": 0,
    "concert": 2
  },
  "model": "appcode.concertanswerscore",
  "pk": 373
},
{
  "fields": {
    "answer": 26,
    "score": 0,
    "concert": 3
  },
  "model": "appcode.concertanswerscore",
  "pk": 374
},
{
  "fields": {
    "answer": 26,
    "score": 0,
    "concert": 4
  },
  "model": "appcode.concertanswerscore",
  "pk": 375
},
{
  "fields": {
    "answer": 26,
    "score": 0,
    "concert": 5
  },
  "model": "appcode.concertanswerscore",
  "pk": 376
},
{
  "fields": {
    "answer": 26,
    "score": 0,
    "concert": 6
  },
  "model": "appcode.concertanswerscore",
  "pk": 377
},
{
  "fields": {
    "answer": 26,
    "score": 0,
    "concert": 7
  },
  "model": "appcode.concertanswerscore",
  "pk": 378
},
{
  "fields": {
    "answer": 26,
    "score": 0,
    "concert": 8
  },
  "model": "appcode.concertanswerscore",
  "pk": 379
},
{
  "fields": {
    "answer": 26,
    "score": 0,
    "concert": 10
  },
  "model": "appcode.concertanswerscore",
  "pk": 380
},
{
  "fields": {
    "answer": 26,
    "score": 0,
    "concert": 12
  },
  "model": "appcode.concertanswerscore",
  "pk": 381
},
{
  "fields": {
    "answer": 26,
    "score": 0,
    "concert": 13
  },
  "model": "appcode.concertanswerscore",
  "pk": 382
},
{
  "fields": {
    "answer": 26,
    "score": 0,
    "concert": 14
  },
  "model": "appcode.concertanswerscore",
  "pk": 383
},
{
  "fields": {
    "answer": 27,
    "score": 0,
    "concert": 1
  },
  "model": "appcode.concertanswerscore",
  "pk": 384
},
{
  "fields": {
    "answer": 27,
    "score": 0,
    "concert": 2
  },
  "model": "appcode.concertanswerscore",
  "pk": 385
},
{
  "fields": {
    "answer": 27,
    "score": 0,
    "concert": 4
  },
  "model": "appcode.concertanswerscore",
  "pk": 386
},
{
  "fields": {
    "answer": 27,
    "score": 0,
    "concert": 5
  },
  "model": "appcode.concertanswerscore",
  "pk": 387
},
{
  "fields": {
    "answer": 27,
    "score": 0,
    "concert": 7
  },
  "model": "appcode.concertanswerscore",
  "pk": 388
},
{
  "fields": {
    "answer": 27,
    "score": 0,
    "concert": 8
  },
  "model": "appcode.concertanswerscore",
  "pk": 389
},
{
  "fields": {
    "answer": 27,
    "score": 0,
    "concert": 9
  },
  "model": "appcode.concertanswerscore",
  "pk": 390
},
{
  "fields": {
    "answer": 27,
    "score": 0,
    "concert": 10
  },
  "model": "appcode.concertanswerscore",
  "pk": 391
},
{
  "fields": {
    "answer": 27,
    "score": 0,
    "concert": 11
  },
  "model": "appcode.concertanswerscore",
  "pk": 392
},
{
  "fields": {
    "answer": 27,
    "score": 0,
    "concert": 14
  },
  "model": "appcode.concertanswerscore",
  "pk": 393
},
{
  "fields": {
    "answer": 28,
    "score": 0,
    "concert": 8
  },
  "model": "appcode.concertanswerscore",
  "pk": 394
},
{
  "fields": {
    "answer": 28,
    "score": 0,
    "concert": 9
  },
  "model": "appcode.concertanswerscore",
  "pk": 395
},
{
  "fields": {
    "answer": 28,
    "score": 0,
    "concert": 11
  },
  "model": "appcode.concertanswerscore",
  "pk": 396
},
{
  "fields": {
    "answer": 28,
    "score": 0,
    "concert": 12
  },
  "model": "appcode.concertanswerscore",
  "pk": 397
},
{
  "fields": {
    "answer": 28,
    "score": 0,
    "concert": 14
  },
  "model": "appcode.concertanswerscore",
  "pk": 398
},
{
  "fields": {
    "answer": 29,
    "score": 0,
    "concert": 1
  },
  "model": "appcode.concertanswerscore",
  "pk": 399
},
{
  "fields": {
    "answer": 29,
    "score": 0,
    "concert": 2
  },
  "model": "appcode.concertanswerscore",
  "pk": 400
},
{
  "fields": {
    "answer": 29,
    "score": 0,
    "concert": 3
  },
  "model": "appcode.concertanswerscore",
  "pk": 401
},
{
  "fields": {
    "answer": 29,
    "score": 0,
    "concert": 4
  },
  "model": "appcode.concertanswerscore",
  "pk": 402
},
{
  "fields": {
    "answer": 29,
    "score": 0,
    "concert": 6
  },
  "model": "appcode.concertanswerscore",
  "pk": 403
},
{
  "fields": {
    "answer": 29,
    "score": 0,
    "concert": 8
  },
  "model": "appcode.concertanswerscore",
  "pk": 404
},
{
  "fields": {
    "answer": 29,
    "score": 0,
    "concert": 10
  },
  "model": "appcode.concertanswerscore",
  "pk": 405
},
{
  "fields": {
    "answer": 29,
    "score": 0,
    "concert": 12
  },
  "model": "appcode.concertanswerscore",
  "pk": 406
},
{
  "fields": {
    "answer": 30,
    "score": 0,
    "concert": 1
  },
  "model": "appcode.concertanswerscore",
  "pk": 407
},
{
  "fields": {
    "answer": 30,
    "score": 0,
    "concert": 2
  },
  "model": "appcode.concertanswerscore",
  "pk": 408
},
{
  "fields": {
    "answer": 30,
    "score": 0,
    "concert": 3
  },
  "model": "appcode.concertanswerscore",
  "pk": 409
},
{
  "fields": {
    "answer": 30,
    "score": 0,
    "concert": 4
  },
  "model": "appcode.concertanswerscore",
  "pk": 410
},
{
  "fields": {
    "answer": 30,
    "score": 0,
    "concert": 5
  },
  "model": "appcode.concertanswerscore",
  "pk": 411
},
{
  "fields": {
    "answer": 30,
    "score": 0,
    "concert": 6
  },
  "model": "appcode.concertanswerscore",
  "pk": 412
},
{
  "fields": {
    "answer": 30,
    "score": 0,
    "concert": 7
  },
  "model": "appcode.concertanswerscore",
  "pk": 413
},
{
  "fields": {
    "answer": 30,
    "score": 0,
    "concert": 8
  },
  "model": "appcode.concertanswerscore",
  "pk": 414
},
{
  "fields": {
    "answer": 30,
    "score": 0,
    "concert": 9
  },
  "model": "appcode.concertanswerscore",
  "pk": 415
},
{
  "fields": {
    "answer": 30,
    "score": 0,
    "concert": 10
  },
  "model": "appcode.concertanswerscore",
  "pk": 416
},
{
  "fields": {
    "answer": 30,
    "score": 0,
    "concert": 11
  },
  "model": "appcode.concertanswerscore",
  "pk": 417
},
{
  "fields": {
    "answer": 30,
    "score": 0,
    "concert": 12
  },
  "model": "appcode.concertanswerscore",
  "pk": 418
},
{
  "fields": {
    "answer": 30,
    "score": 0,
    "concert": 13
  },
  "model": "appcode.concertanswerscore",
  "pk": 419
},
{
  "fields": {
    "answer": 30,
    "score": 0,
    "concert": 14
  },
  "model": "appcode.concertanswerscore",
  "pk": 420
},
{
  "fields": {
    "answer": 31,
    "score": 0,
    "concert": 1
  },
  "model": "appcode.concertanswerscore",
  "pk": 421
},
{
  "fields": {
    "answer": 31,
    "score": 0,
    "concert": 2
  },
  "model": "appcode.concertanswerscore",
  "pk": 422
},
{
  "fields": {
    "answer": 31,
    "score": 0,
    "concert": 3
  },
  "model": "appcode.concertanswerscore",
  "pk": 423
},
{
  "fields": {
    "answer": 31,
    "score": 0,
    "concert": 4
  },
  "model": "appcode.concertanswerscore",
  "pk": 424
},
{
  "fields": {
    "answer": 31,
    "score": 0,
    "concert": 5
  },
  "model": "appcode.concertanswerscore",
  "pk": 425
},
{
  "fields": {
    "answer": 31,
    "score": 0,
    "concert": 6
  },
  "model": "appcode.concertanswerscore",
  "pk": 426
},
{
  "fields": {
    "answer": 31,
    "score": 0,
    "concert": 7
  },
  "model": "appcode.concertanswerscore",
  "pk": 427
},
{
  "fields": {
    "answer": 31,
    "score": 0,
    "concert": 8
  },
  "model": "appcode.concertanswerscore",
  "pk": 428
},
{
  "fields": {
    "answer": 31,
    "score": 0,
    "concert": 9
  },
  "model": "appcode.concertanswerscore",
  "pk": 429
},
{
  "fields": {
    "answer": 31,
    "score": 0,
    "concert": 10
  },
  "model": "appcode.concertanswerscore",
  "pk": 430
},
{
  "fields": {
    "answer": 31,
    "score": 0,
    "concert": 11
  },
  "model": "appcode.concertanswerscore",
  "pk": 431
},
{
  "fields": {
    "answer": 31,
    "score": 0,
    "concert": 12
  },
  "model": "appcode.concertanswerscore",
  "pk": 432
},
{
  "fields": {
    "answer": 31,
    "score": 0,
    "concert": 13
  },
  "model": "appcode.concertanswerscore",
  "pk": 433
},
{
  "fields": {
    "answer": 31,
    "score": 0,
    "concert": 14
  },
  "model": "appcode.concertanswerscore",
  "pk": 434
},
{
  "fields": {
    "answer": 32,
    "score": 0,
    "concert": 1
  },
  "model": "appcode.concertanswerscore",
  "pk": 435
},
{
  "fields": {
    "answer": 32,
    "score": 0,
    "concert": 2
  },
  "model": "appcode.concertanswerscore",
  "pk": 436
},
{
  "fields": {
    "answer": 32,
    "score": 0,
    "concert": 3
  },
  "model": "appcode.concertanswerscore",
  "pk": 437
},
{
  "fields": {
    "answer": 32,
    "score": 0,
    "concert": 4
  },
  "model": "appcode.concertanswerscore",
  "pk": 438
},
{
  "fields": {
    "answer": 32,
    "score": 0,
    "concert": 5
  },
  "model": "appcode.concertanswerscore",
  "pk": 439
},
{
  "fields": {
    "answer": 32,
    "score": 0,
    "concert": 6
  },
  "model": "appcode.concertanswerscore",
  "pk": 440
},
{
  "fields": {
    "answer": 32,
    "score": 0,
    "concert": 7
  },
  "model": "appcode.concertanswerscore",
  "pk": 441
},
{
  "fields": {
    "answer": 32,
    "score": 0,
    "concert": 8
  },
  "model": "appcode.concertanswerscore",
  "pk": 442
},
{
  "fields": {
    "answer": 32,
    "score": 0,
    "concert": 9
  },
  "model": "appcode.concertanswerscore",
  "pk": 443
},
{
  "fields": {
    "answer": 32,
    "score": 0,
    "concert": 10
  },
  "model": "appcode.concertanswerscore",
  "pk": 444
},
{
  "fields": {
    "answer": 32,
    "score": 0,
    "concert": 11
  },
  "model": "appcode.concertanswerscore",
  "pk": 445
},
{
  "fields": {
    "answer": 32,
    "score": 0,
    "concert": 12
  },
  "model": "appcode.concertanswerscore",
  "pk": 446
},
{
  "fields": {
    "answer": 32,
    "score": 0,
    "concert": 13
  },
  "model": "appcode.concertanswerscore",
  "pk": 447
},
{
  "fields": {
    "answer": 32,
    "score": 0,
    "concert": 14
  },
  "model": "appcode.concertanswerscore",
  "pk": 448
},
{
  "fields": {
    "answer": 33,
    "score": 0,
    "concert": 1
  },
  "model": "appcode.concertanswerscore",
  "pk": 449
},
{
  "fields": {
    "answer": 33,
    "score": 0,
    "concert": 2
  },
  "model": "appcode.concertanswerscore",
  "pk": 450
},
{
  "fields": {
    "answer": 33,
    "score": 0,
    "concert": 3
  },
  "model": "appcode.concertanswerscore",
  "pk": 451
},
{
  "fields": {
    "answer": 33,
    "score": 0,
    "concert": 4
  },
  "model": "appcode.concertanswerscore",
  "pk": 452
},
{
  "fields": {
    "answer": 33,
    "score": 0,
    "concert": 5
  },
  "model": "appcode.concertanswerscore",
  "pk": 453
},
{
  "fields": {
    "answer": 33,
    "score": 0,
    "concert": 6
  },
  "model": "appcode.concertanswerscore",
  "pk": 454
},
{
  "fields": {
    "answer": 33,
    "score": 0,
    "concert": 7
  },
  "model": "appcode.concertanswerscore",
  "pk": 455
},
{
  "fields": {
    "answer": 33,
    "score": 0,
    "concert": 8
  },
  "model": "appcode.concertanswerscore",
  "pk": 456
},
{
  "fields": {
    "answer": 33,
    "score": 0,
    "concert": 9
  },
  "model": "appcode.concertanswerscore",
  "pk": 457
},
{
  "fields": {
    "answer": 33,
    "score": 0,
    "concert": 10
  },
  "model": "appcode.concertanswerscore",
  "pk": 458
},
{
  "fields": {
    "answer": 33,
    "score": 0,
    "concert": 11
  },
  "model": "appcode.concertanswerscore",
  "pk": 459
},
{
  "fields": {
    "answer": 33,
    "score": 0,
    "concert": 12
  },
  "model": "appcode.concertanswerscore",
  "pk": 460
},
{
  "fields": {
    "answer": 33,
    "score": 0,
    "concert": 13
  },
  "model": "appcode.concertanswerscore",
  "pk": 461
},
{
  "fields": {
    "answer": 33,
    "score": 0,
    "concert": 14
  },
  "model": "appcode.concertanswerscore",
  "pk": 462
},
{
  "fields": {
    "answer": 34,
    "score": 0,
    "concert": 1
  },
  "model": "appcode.concertanswerscore",
  "pk": 463
},
{
  "fields": {
    "answer": 34,
    "score": 0,
    "concert": 2
  },
  "model": "appcode.concertanswerscore",
  "pk": 464
},
{
  "fields": {
    "answer": 34,
    "score": 0,
    "concert": 3
  },
  "model": "appcode.concertanswerscore",
  "pk": 465
},
{
  "fields": {
    "answer": 34,
    "score": 0,
    "concert": 4
  },
  "model": "appcode.concertanswerscore",
  "pk": 466
},
{
  "fields": {
    "answer": 34,
    "score": 0,
    "concert": 5
  },
  "model": "appcode.concertanswerscore",
  "pk": 467
},
{
  "fields": {
    "answer": 34,
    "score": 0,
    "concert": 6
  },
  "model": "appcode.concertanswerscore",
  "pk": 468
},
{
  "fields": {
    "answer": 34,
    "score": 0,
    "concert": 7
  },
  "model": "appcode.concertanswerscore",
  "pk": 469
},
{
  "fields": {
    "answer": 34,
    "score": 0,
    "concert": 8
  },
  "model": "appcode.concertanswerscore",
  "pk": 470
},
{
  "fields": {
    "answer": 34,
    "score": 0,
    "concert": 9
  },
  "model": "appcode.concertanswerscore",
  "pk": 471
},
{
  "fields": {
    "answer": 34,
    "score": 0,
    "concert": 10
  },
  "model": "appcode.concertanswerscore",
  "pk": 472
},
{
  "fields": {
    "answer": 34,
    "score": 0,
    "concert": 11
  },
  "model": "appcode.concertanswerscore",
  "pk": 473
},
{
  "fields": {
    "answer": 34,
    "score": 0,
    "concert": 12
  },
  "model": "appcode.concertanswerscore",
  "pk": 474
},
{
  "fields": {
    "answer": 34,
    "score": 0,
    "concert": 13
  },
  "model": "appcode.concertanswerscore",
  "pk": 475
},
{
  "fields": {
    "answer": 34,
    "score": 0,
    "concert": 14
  },
  "model": "appcode.concertanswerscore",
  "pk": 476
},
{
  "fields": {
    "answer": 35,
    "score": 0,
    "concert": 1
  },
  "model": "appcode.concertanswerscore",
  "pk": 477
},
{
  "fields": {
    "answer": 35,
    "score": 0,
    "concert": 2
  },
  "model": "appcode.concertanswerscore",
  "pk": 478
},
{
  "fields": {
    "answer": 35,
    "score": 0,
    "concert": 3
  },
  "model": "appcode.concertanswerscore",
  "pk": 479
},
{
  "fields": {
    "answer": 35,
    "score": 0,
    "concert": 4
  },
  "model": "appcode.concertanswerscore",
  "pk": 480
},
{
  "fields": {
    "answer": 35,
    "score": 0,
    "concert": 5
  },
  "model": "appcode.concertanswerscore",
  "pk": 481
},
{
  "fields": {
    "answer": 35,
    "score": 0,
    "concert": 6
  },
  "model": "appcode.concertanswerscore",
  "pk": 482
},
{
  "fields": {
    "answer": 35,
    "score": 0,
    "concert": 7
  },
  "model": "appcode.concertanswerscore",
  "pk": 483
},
{
  "fields": {
    "answer": 35,
    "score": 0,
    "concert": 8
  },
  "model": "appcode.concertanswerscore",
  "pk": 484
},
{
  "fields": {
    "answer": 35,
    "score": 0,
    "concert": 9
  },
  "model": "appcode.concertanswerscore",
  "pk": 485
},
{
  "fields": {
    "answer": 35,
    "score": 0,
    "concert": 10
  },
  "model": "appcode.concertanswerscore",
  "pk": 486
},
{
  "fields": {
    "answer": 35,
    "score": 0,
    "concert": 11
  },
  "model": "appcode.concertanswerscore",
  "pk": 487
},
{
  "fields": {
    "answer": 35,
    "score": 0,
    "concert": 12
  },
  "model": "appcode.concertanswerscore",
  "pk": 488
},
{
  "fields": {
    "answer": 35,
    "score": 0,
    "concert": 13
  },
  "model": "appcode.concertanswerscore",
  "pk": 489
},
{
  "fields": {
    "answer": 35,
    "score": 0,
    "concert": 14
  },
  "model": "appcode.concertanswerscore",
  "pk": 490
},
{
  "fields": {
    "answer": 36,
    "score": 0,
    "concert": 1
  },
  "model": "appcode.concertanswerscore",
  "pk": 491
},
{
  "fields": {
    "answer": 36,
    "score": 0,
    "concert": 2
  },
  "model": "appcode.concertanswerscore",
  "pk": 492
},
{
  "fields": {
    "answer": 36,
    "score": 0,
    "concert": 3
  },
  "model": "appcode.concertanswerscore",
  "pk": 493
},
{
  "fields": {
    "answer": 36,
    "score": 0,
    "concert": 4
  },
  "model": "appcode.concertanswerscore",
  "pk": 494
},
{
  "fields": {
    "answer": 36,
    "score": 0,
    "concert": 5
  },
  "model": "appcode.concertanswerscore",
  "pk": 495
},
{
  "fields": {
    "answer": 36,
    "score": 0,
    "concert": 6
  },
  "model": "appcode.concertanswerscore",
  "pk": 496
},
{
  "fields": {
    "answer": 36,
    "score": 0,
    "concert": 7
  },
  "model": "appcode.concertanswerscore",
  "pk": 497
},
{
  "fields": {
    "answer": 36,
    "score": 0,
    "concert": 8
  },
  "model": "appcode.concertanswerscore",
  "pk": 498
},
{
  "fields": {
    "answer": 36,
    "score": 0,
    "concert": 9
  },
  "model": "appcode.concertanswerscore",
  "pk": 499
},
{
  "fields": {
    "answer": 36,
    "score": 0,
    "concert": 10
  },
  "model": "appcode.concertanswerscore",
  "pk": 500
},
{
  "fields": {
    "answer": 36,
    "score": 0,
    "concert": 11
  },
  "model": "appcode.concertanswerscore",
  "pk": 501
},
{
  "fields": {
    "answer": 36,
    "score": 0,
    "concert": 12
  },
  "model": "appcode.concertanswerscore",
  "pk": 502
},
{
  "fields": {
    "answer": 36,
    "score": 0,
    "concert": 13
  },
  "model": "appcode.concertanswerscore",
  "pk": 503
},
{
  "fields": {
    "answer": 36,
    "score": 0,
    "concert": 14
  },
  "model": "appcode.concertanswerscore",
  "pk": 504
},
{
  "fields": {
    "answer": 37,
    "score": 0,
    "concert": 1
  },
  "model": "appcode.concertanswerscore",
  "pk": 505
},
{
  "fields": {
    "answer": 37,
    "score": 0,
    "concert": 2
  },
  "model": "appcode.concertanswerscore",
  "pk": 506
},
{
  "fields": {
    "answer": 37,
    "score": 0,
    "concert": 3
  },
  "model": "appcode.concertanswerscore",
  "pk": 507
},
{
  "fields": {
    "answer": 37,
    "score": 0,
    "concert": 4
  },
  "model": "appcode.concertanswerscore",
  "pk": 508
},
{
  "fields": {
    "answer": 37,
    "score": 0,
    "concert": 5
  },
  "model": "appcode.concertanswerscore",
  "pk": 509
},
{
  "fields": {
    "answer": 37,
    "score": 0,
    "concert": 6
  },
  "model": "appcode.concertanswerscore",
  "pk": 510
},
{
  "fields": {
    "answer": 37,
    "score": 0,
    "concert": 7
  },
  "model": "appcode.concertanswerscore",
  "pk": 511
},
{
  "fields": {
    "answer": 37,
    "score": 0,
    "concert": 8
  },
  "model": "appcode.concertanswerscore",
  "pk": 512
},
{
  "fields": {
    "answer": 37,
    "score": 0,
    "concert": 9
  },
  "model": "appcode.concertanswerscore",
  "pk": 513
},
{
  "fields": {
    "answer": 37,
    "score": 0,
    "concert": 10
  },
  "model": "appcode.concertanswerscore",
  "pk": 514
},
{
  "fields": {
    "answer": 37,
    "score": 0,
    "concert": 11
  },
  "model": "appcode.concertanswerscore",
  "pk": 515
},
{
  "fields": {
    "answer": 37,
    "score": 0,
    "concert": 12
  },
  "model": "appcode.concertanswerscore",
  "pk": 516
},
{
  "fields": {
    "answer": 37,
    "score": 0,
    "concert": 13
  },
  "model": "appcode.concertanswerscore",
  "pk": 517
},
{
  "fields": {
    "answer": 37,
    "score": 0,
    "concert": 14
  },
  "model": "appcode.concertanswerscore",
  "pk": 518
},
{
  "fields": {
    "answer": 38,
    "score": 0,
    "concert": 1
  },
  "model": "appcode.concertanswerscore",
  "pk": 519
},
{
  "fields": {
    "answer": 38,
    "score": 0,
    "concert": 2
  },
  "model": "appcode.concertanswerscore",
  "pk": 520
},
{
  "fields": {
    "answer": 38,
    "score": 0,
    "concert": 3
  },
  "model": "appcode.concertanswerscore",
  "pk": 521
},
{
  "fields": {
    "answer": 38,
    "score": 0,
    "concert": 4
  },
  "model": "appcode.concertanswerscore",
  "pk": 522
},
{
  "fields": {
    "answer": 38,
    "score": 0,
    "concert": 5
  },
  "model": "appcode.concertanswerscore",
  "pk": 523
},
{
  "fields": {
    "answer": 38,
    "score": 0,
    "concert": 6
  },
  "model": "appcode.concertanswerscore",
  "pk": 524
},
{
  "fields": {
    "answer": 38,
    "score": 0,
    "concert": 7
  },
  "model": "appcode.concertanswerscore",
  "pk": 525
},
{
  "fields": {
    "answer": 38,
    "score": 0,
    "concert": 8
  },
  "model": "appcode.concertanswerscore",
  "pk": 526
},
{
  "fields": {
    "answer": 38,
    "score": 0,
    "concert": 9
  },
  "model": "appcode.concertanswerscore",
  "pk": 527
},
{
  "fields": {
    "answer": 38,
    "score": 0,
    "concert": 10
  },
  "model": "appcode.concertanswerscore",
  "pk": 528
},
{
  "fields": {
    "answer": 38,
    "score": 0,
    "concert": 11
  },
  "model": "appcode.concertanswerscore",
  "pk": 529
},
{
  "fields": {
    "answer": 38,
    "score": 0,
    "concert": 12
  },
  "model": "appcode.concertanswerscore",
  "pk": 530
},
{
  "fields": {
    "answer": 38,
    "score": 0,
    "concert": 13
  },
  "model": "appcode.concertanswerscore",
  "pk": 531
},
{
  "fields": {
    "answer": 38,
    "score": 0,
    "concert": 14
  },
  "model": "appcode.concertanswerscore",
  "pk": 532
},
{
  "fields": {
    "answer": 39,
    "score": 0,
    "concert": 1
  },
  "model": "appcode.concertanswerscore",
  "pk": 533
},
{
  "fields": {
    "answer": 39,
    "score": 0,
    "concert": 2
  },
  "model": "appcode.concertanswerscore",
  "pk": 534
},
{
  "fields": {
    "answer": 39,
    "score": 0,
    "concert": 3
  },
  "model": "appcode.concertanswerscore",
  "pk": 535
},
{
  "fields": {
    "answer": 39,
    "score": 0,
    "concert": 4
  },
  "model": "appcode.concertanswerscore",
  "pk": 536
},
{
  "fields": {
    "answer": 39,
    "score": 0,
    "concert": 5
  },
  "model": "appcode.concertanswerscore",
  "pk": 537
},
{
  "fields": {
    "answer": 39,
    "score": 0,
    "concert": 6
  },
  "model": "appcode.concertanswerscore",
  "pk": 538
},
{
  "fields": {
    "answer": 39,
    "score": 0,
    "concert": 7
  },
  "model": "appcode.concertanswerscore",
  "pk": 539
},
{
  "fields": {
    "answer": 39,
    "score": 0,
    "concert": 8
  },
  "model": "appcode.concertanswerscore",
  "pk": 540
},
{
  "fields": {
    "answer": 39,
    "score": 0,
    "concert": 9
  },
  "model": "appcode.concertanswerscore",
  "pk": 541
},
{
  "fields": {
    "answer": 39,
    "score": 0,
    "concert": 10
  },
  "model": "appcode.concertanswerscore",
  "pk": 542
},
{
  "fields": {
    "answer": 39,
    "score": 0,
    "concert": 11
  },
  "model": "appcode.concertanswerscore",
  "pk": 543
},
{
  "fields": {
    "answer": 39,
    "score": 0,
    "concert": 12
  },
  "model": "appcode.concertanswerscore",
  "pk": 544
},
{
  "fields": {
    "answer": 39,
    "score": 0,
    "concert": 13
  },
  "model": "appcode.concertanswerscore",
  "pk": 545
},
{
  "fields": {
    "answer": 39,
    "score": 0,
    "concert": 14
  },
  "model": "appcode.concertanswerscore",
  "pk": 546
}
]
